[{"playerWallData_Right":null,"playerWallData_Left":null,"localPosition":"4,-3,0","localRotation":"0,0,0","localScale":"8,6,6.824931","left_x":0,"parentName":"collider","luaName":"FlatSurface","param":""},{"surface_localScale":"195,0.1,100","target_localPosition":null,"localPosition":"97.5,-6.1,0","localRotation":"0,0,0","localScale":"1,1,1","left_x":0,"parentName":"revive","luaName":"ReviveSurface","param":"10"},{"localPosition":"2.41,0.63,0","localRotation":"0,0,0","localScale":"1,1,1","left_x":1,"parentName":"bouncing","luaName":"HolyLandingPointMark","param":""},{"localPosition":"4.8,1.4,0","localRotation":"0,0,0","localScale":"1,1,1","left_x":4,"parentName":"bouncing","luaName":"RhubarbDuckPointMark","param":""},{"trigger_localPosition":"-4.9,0.04,0","trigger_localRotation":"0,0,0","trigger_localScale":"1,1,1","trigger_size":"1,8,3","objects":[{"luaName":"KoffingEnemy","localPosition":"2.199997,5,0","localRotation":"0,90.00001,0","localScale":"2.5,2.5,-2.5","childLocalScale":"1,1,1","material_id":"15030000","path":[{"speed":40.0,"delay":1.05,"loopType":"none","easeType":"easeOutExpo","rotateAngle":"0,0,0","nodes":["0,0,0","0,-9,0"]}]},{"luaName":"KoffingEnemy","localPosition":"-2.300003,5,0","localRotation":"0,90.00001,0","localScale":"2.5,2.5,-2.5","childLocalScale":"1,1,1","material_id":"15030000","path":[{"speed":40.0,"delay":0.55,"loopType":"none","easeType":"easeOutExpo","rotateAngle":"0,0,0","nodes":["0,0,0","0,-9,0"]}]},{"luaName":"KoffingEnemy","localPosition":"6.699982,5,0","localRotation":"0,90.00001,0","localScale":"2.499999,2.5,-2.499999","childLocalScale":"1,1,1","material_id":"15030000","path":[{"speed":40.0,"delay":1.55,"loopType":"none","easeType":"easeOutExpo","rotateAngle":"0,0,0","nodes":["0,0,0","0,-9,0"]}]}],"localPosition":"11.67001,4,0","localRotation":"0,0,0","localScale":"1,1,1","left_x":6,"parentName":"monster","luaName":"AnimTriggerItem","param":""},{"trigger_localPosition":"-3.47,-5.03,0","trigger_localRotation":"0,0,0","trigger_localScale":"1,1,1","trigger_size":"1,8,3","objects":[{"luaName":"MovingSurface","localPosition":"-2,-9.5,0","localRotation":"0,0,0","localScale":"4,1,7","childLocalScale":"0.1428571,1,0.25","material_id":"scenes_common_cloudroad01c","path":[{"speed":15.0,"delay":0.4,"loopType":"none","easeType":"linear","rotateAngle":"0,0,0","nodes":["0,0,0","0,-12,0"]}]},{"luaName":"MovingSurface","localPosition":"2,-9.5,0","localRotation":"0,0,0","localScale":"4,1,7","childLocalScale":"0.1428571,1,0.25","material_id":"scenes_common_cloudroad01c","path":[{"speed":15.0,"delay":0.9,"loopType":"none","easeType":"linear","rotateAngle":"0,0,0","nodes":["0,0,0","0,-12,0"]}]},{"luaName":"MovingSurface","localPosition":"6,-9.5,0","localRotation":"0,0,0","localScale":"4,1,7","childLocalScale":"0.1428571,1,0.25","material_id":"scenes_common_cloudroad01c","path":[{"speed":15.0,"delay":1.3,"loopType":"none","easeType":"linear","rotateAngle":"0,0,0","nodes":["0,0,0","0,-12,0"]}]}],"localPosition":"12,9,0","localRotation":"0,0,0","localScale":"1,1,1","left_x":8,"parentName":"monster","luaName":"AnimTriggerItem","param":""},{"items":[{"localPosition":"-8.47,-1.04,0","localRotation":"0,0,0","localScale":"-0.75,0.75,0.75","material_id":"15020000"},{"localPosition":"0.9,-1.04,0","localRotation":"0,0,0","localScale":"-0.75,0.75,0.75","material_id":"15020000"},{"localPosition":"-8.22,-0.39,0","localRotation":"0,0,0","localScale":"-0.75,0.75,0.75","material_id":"15020000"},{"localPosition":"0.66,-0.39,0","localRotation":"0,0,0","localScale":"-0.75,0.75,0.75","material_id":"15020000"},{"localPosition":"-7.87,0.25,0","localRotation":"0,0,0","localScale":"-0.75,0.75,0.75","material_id":"15020000"},{"localPosition":"0.38,0.25,0","localRotation":"0,0,0","localScale":"-0.75,0.75,0.75","material_id":"15020000"},{"localPosition":"-7.43,0.89,0","localRotation":"0,0,0","localScale":"-0.75,0.75,0.75","material_id":"15020000"},{"localPosition":"-0.11,0.89,0","localRotation":"0,0,0","localScale":"-0.75,0.75,0.75","material_id":"15020000"},{"localPosition":"-6.83,1.54,0","localRotation":"0,0,0","localScale":"-0.75,0.75,0.75","material_id":"15020000"},{"localPosition":"-0.7,1.54,0","localRotation":"0,0,0","localScale":"-0.75,0.75,0.75","material_id":"15020000"},{"localPosition":"-6.09,2.02,0","localRotation":"0,0,0","localScale":"-0.75,0.75,0.75","material_id":"15020000"},{"localPosition":"-1.5,2.02,0","localRotation":"0,0,0","localScale":"-0.75,0.75,0.75","material_id":"15020000"},{"localPosition":"-2.29,2.32,0","localRotation":"0,0,0","localScale":"-0.75,0.75,0.75","material_id":"15020000"},{"localPosition":"-5.28,2.32,0","localRotation":"0,0,0","localScale":"-0.75,0.75,0.75","material_id":"15020000"},{"localPosition":"-4.55,2.32,0","localRotation":"0,0,0","localScale":"-0.75,0.75,0.75","material_id":"15020000"},{"localPosition":"-3.05,2.32,0","localRotation":"0,0,0","localScale":"-0.75,0.75,0.75","material_id":"15020000"},{"localPosition":"-3.8,2.32,0","localRotation":"0,0,0","localScale":"-0.75,0.75,0.75","material_id":"15020000"}],"localPosition":"22.72744,1.881337,0","localRotation":"0,0,0","localScale":"1,1,1","left_x":13,"parentName":"item","luaName":"EliminateItemGroup","param":""},{"collider_center":null,"collider_radius":null,"collider_height":null,"localPosition":"19.1,3.87,0","localRotation":"0,90.00001,0","localScale":"2,2,-2","left_x":18,"parentName":"monster","luaName":"NormalBirdEnemy","param":"15102000"},{"playerWallData_Right":null,"playerWallData_Left":null,"localPosition":"23,-3,0","localRotation":"0,0,0","localScale":"6,6,6.824931","left_x":20,"parentName":"collider","luaName":"FlatSurface","param":""},{"localPosition":"20.89,0.59,0","localRotation":"0,0,0","localScale":"1,1,1","left_x":20,"parentName":"bouncing","luaName":"RevivePointMark","param":""},{"localPosition":"22.48,2.25,0","localRotation":"0,0,0","localScale":"1,1,1","left_x":21,"parentName":"bouncing","luaName":"RhubarbDuckPointMark","param":""},{"trigger_localPosition":"-4.9,0.04,0","trigger_localRotation":"0,0,0","trigger_localScale":"1,1,1","trigger_size":"1,8,3","objects":[{"luaName":"KoffingEnemy","localPosition":"6.699997,5,0","localRotation":"0,90.00001,0","localScale":"2.499999,2.5,-2.499999","childLocalScale":"1,1,1","material_id":"15030000","path":[{"speed":40.0,"delay":1.55,"loopType":"none","easeType":"easeOutExpo","rotateAngle":"0,0,0","nodes":["0,0,0","0,-9,0"]}]},{"luaName":"KoffingEnemy","localPosition":"2.199997,5,0","localRotation":"0,90.00001,0","localScale":"2.5,2.5,-2.5","childLocalScale":"1,1,1","material_id":"15030000","path":[{"speed":40.0,"delay":1.05,"loopType":"none","easeType":"easeOutExpo","rotateAngle":"0,0,0","nodes":["0,0,0","0,-9,0"]}]},{"luaName":"KoffingEnemy","localPosition":"-2.300003,5,0","localRotation":"0,90.00001,0","localScale":"2.5,2.5,-2.5","childLocalScale":"1,1,1","material_id":"15030000","path":[{"speed":40.0,"delay":0.55,"loopType":"none","easeType":"easeOutExpo","rotateAngle":"0,0,0","nodes":["0,0,0","0,-9,0"]}]}],"localPosition":"30.09,4,0","localRotation":"0,0,0","localScale":"1,1,1","left_x":24,"parentName":"monster","luaName":"AnimTriggerItem","param":""},{"trigger_localPosition":"-3.47,-5.03,0","trigger_localRotation":"0,0,0","trigger_localScale":"1,1,1","trigger_size":"1,8,3","objects":[{"luaName":"MovingSurface","localPosition":"1.98999,-9.5,0","localRotation":"0,0,0","localScale":"4,1,7","childLocalScale":"0.1428571,1,0.25","material_id":"scenes_common_cloudroad01c","path":[{"speed":15.0,"delay":0.9,"loopType":"none","easeType":"linear","rotateAngle":"0,0,0","nodes":["0,0,0","0,-12,0"]}]},{"luaName":"MovingSurface","localPosition":"-2.01001,-9.5,0","localRotation":"0,0,0","localScale":"4,1,7","childLocalScale":"0.1428571,1,0.25","material_id":"scenes_common_cloudroad01c","path":[{"speed":15.0,"delay":0.4,"loopType":"none","easeType":"linear","rotateAngle":"0,0,0","nodes":["0,0,0","0,-12,0"]}]}],"localPosition":"30.01001,9,0","localRotation":"0,0,0","localScale":"1,1,1","left_x":26,"parentName":"monster","luaName":"AnimTriggerItem","param":""},{"items":[{"localPosition":"-8.47,-1.04,0","localRotation":"0,0,0","localScale":"-0.75,0.75,0.75","material_id":"15020000"},{"localPosition":"0.9,-1.04,0","localRotation":"0,0,0","localScale":"-0.75,0.75,0.75","material_id":"15020000"},{"localPosition":"-8.22,-0.39,0","localRotation":"0,0,0","localScale":"-0.75,0.75,0.75","material_id":"15020000"},{"localPosition":"0.66,-0.39,0","localRotation":"0,0,0","localScale":"-0.75,0.75,0.75","material_id":"15020000"},{"localPosition":"-7.87,0.25,0","localRotation":"0,0,0","localScale":"-0.75,0.75,0.75","material_id":"15020000"},{"localPosition":"0.38,0.25,0","localRotation":"0,0,0","localScale":"-0.75,0.75,0.75","material_id":"15020000"},{"localPosition":"-7.43,0.89,0","localRotation":"0,0,0","localScale":"-0.75,0.75,0.75","material_id":"15020000"},{"localPosition":"-0.11,0.89,0","localRotation":"0,0,0","localScale":"-0.75,0.75,0.75","material_id":"15020000"},{"localPosition":"-6.83,1.54,0","localRotation":"0,0,0","localScale":"-0.75,0.75,0.75","material_id":"15020000"},{"localPosition":"-0.7,1.54,0","localRotation":"0,0,0","localScale":"-0.75,0.75,0.75","material_id":"15020000"},{"localPosition":"-6.09,2.02,0","localRotation":"0,0,0","localScale":"-0.75,0.75,0.75","material_id":"15020000"},{"localPosition":"-1.5,2.02,0","localRotation":"0,0,0","localScale":"-0.75,0.75,0.75","material_id":"15020000"},{"localPosition":"-2.29,2.32,0","localRotation":"0,0,0","localScale":"-0.75,0.75,0.75","material_id":"15020000"},{"localPosition":"-5.28,2.32,0","localRotation":"0,0,0","localScale":"-0.75,0.75,0.75","material_id":"15020000"},{"localPosition":"-4.55,2.32,0","localRotation":"0,0,0","localScale":"-0.75,0.75,0.75","material_id":"15020000"},{"localPosition":"-3.05,2.32,0","localRotation":"0,0,0","localScale":"-0.75,0.75,0.75","material_id":"15020000"},{"localPosition":"-3.8,2.32,0","localRotation":"0,0,0","localScale":"-0.75,0.75,0.75","material_id":"15020000"}],"localPosition":"37.83,1.88,0","localRotation":"0,0,0","localScale":"1,1,1","left_x":28,"parentName":"item","luaName":"EliminateItemGroup","param":""},{"collider_center":null,"collider_radius":null,"collider_height":null,"localPosition":"34.28,3.87,0","localRotation":"0,90.00001,0","localScale":"2,2,-2","left_x":33,"parentName":"monster","luaName":"NormalBirdEnemy","param":"15102000"},{"playerWallData_Right":null,"playerWallData_Left":null,"localPosition":"37,-3,0","localRotation":"0,0,0","localScale":"6,6,6.824931","left_x":34,"parentName":"collider","luaName":"FlatSurface","param":""},{"localPosition":"35.44,2.38,0","localRotation":"0,0,0","localScale":"1,1,1","left_x":34,"parentName":"bouncing","luaName":"RhubarbDuckPointMark","param":""},{"localPosition":"34.77,0.56,0","localRotation":"0,0,0","localScale":"1,1,1","left_x":34,"parentName":"bouncing","luaName":"RevivePointMark","param":""},{"trigger_localPosition":"-3.47,-5.03,0","trigger_localRotation":"0,0,0","trigger_localScale":"1,1,1","trigger_size":"1,8,3","objects":[{"luaName":"MovingSurface","localPosition":"5.980011,-9.5,0","localRotation":"0,0,0","localScale":"4,1,7","childLocalScale":"0.1428571,1,0.25","material_id":"scenes_common_cloudroad01c","path":[{"speed":15.0,"delay":1.3,"loopType":"none","easeType":"linear","rotateAngle":"0,0,0","nodes":["0,0,0","0,-12,0"]}]},{"luaName":"MovingSurface","localPosition":"1.980011,-9.5,0","localRotation":"0,0,0","localScale":"4,1,7","childLocalScale":"0.1428571,1,0.25","material_id":"scenes_common_cloudroad01c","path":[{"speed":15.0,"delay":0.8,"loopType":"none","easeType":"linear","rotateAngle":"0,0,0","nodes":["0,0,0","0,-12,0"]}]},{"luaName":"MovingSurface","localPosition":"-2.019989,-9.5,0","localRotation":"0,0,0","localScale":"4,1,7","childLocalScale":"0.1428571,1,0.25","material_id":"scenes_common_cloudroad01c","path":[{"speed":15.0,"delay":0.4,"loopType":"none","easeType":"linear","rotateAngle":"0,0,0","nodes":["0,0,0","0,-12,0"]}]}],"localPosition":"44.01999,9,0","localRotation":"0,0,0","localScale":"1,1,1","left_x":40,"parentName":"monster","luaName":"AnimTriggerItem","param":""},{"items":[{"localPosition":"-8.47,-1.04,0","localRotation":"0,0,0","localScale":"-0.75,0.75,0.75","material_id":"15020000"},{"localPosition":"0.9,-1.04,0","localRotation":"0,0,0","localScale":"-0.75,0.75,0.75","material_id":"15020000"},{"localPosition":"-8.22,-0.39,0","localRotation":"0,0,0","localScale":"-0.75,0.75,0.75","material_id":"15020000"},{"localPosition":"0.66,-0.39,0","localRotation":"0,0,0","localScale":"-0.75,0.75,0.75","material_id":"15020000"},{"localPosition":"-7.87,0.25,0","localRotation":"0,0,0","localScale":"-0.75,0.75,0.75","material_id":"15020000"},{"localPosition":"0.38,0.25,0","localRotation":"0,0,0","localScale":"-0.75,0.75,0.75","material_id":"15020000"},{"localPosition":"-7.43,0.89,0","localRotation":"0,0,0","localScale":"-0.75,0.75,0.75","material_id":"15020000"},{"localPosition":"-0.11,0.89,0","localRotation":"0,0,0","localScale":"-0.75,0.75,0.75","material_id":"15020000"},{"localPosition":"-6.83,1.54,0","localRotation":"0,0,0","localScale":"-0.75,0.75,0.75","material_id":"15020000"},{"localPosition":"-0.7,1.54,0","localRotation":"0,0,0","localScale":"-0.75,0.75,0.75","material_id":"15020000"},{"localPosition":"-6.09,2.02,0","localRotation":"0,0,0","localScale":"-0.75,0.75,0.75","material_id":"15020000"},{"localPosition":"-1.5,2.02,0","localRotation":"0,0,0","localScale":"-0.75,0.75,0.75","material_id":"15020000"},{"localPosition":"-2.29,2.32,0","localRotation":"0,0,0","localScale":"-0.75,0.75,0.75","material_id":"15020000"},{"localPosition":"-5.28,2.32,0","localRotation":"0,0,0","localScale":"-0.75,0.75,0.75","material_id":"15020000"},{"localPosition":"-4.55,2.32,0","localRotation":"0,0,0","localScale":"-0.75,0.75,0.75","material_id":"15020000"},{"localPosition":"-3.05,2.32,0","localRotation":"0,0,0","localScale":"-0.75,0.75,0.75","material_id":"15020000"},{"localPosition":"-3.8,2.32,0","localRotation":"0,0,0","localScale":"-0.75,0.75,0.75","material_id":"15020000"}],"localPosition":"53.86,1.88,0","localRotation":"0,0,0","localScale":"1,1,1","left_x":44,"parentName":"item","luaName":"EliminateItemGroup","param":""},{"collider_center":null,"collider_radius":null,"collider_height":null,"localPosition":"50.16,3.87,0","localRotation":"0,90.00001,0","localScale":"2,2,-2","left_x":49,"parentName":"monster","luaName":"NormalBirdEnemy","param":"15102000"},{"playerWallData_Right":null,"playerWallData_Left":null,"localPosition":"55,-3,0","localRotation":"0,0,0","localScale":"6,6,6.824931","left_x":52,"parentName":"collider","luaName":"FlatSurface","param":""},{"localPosition":"52.69,0.59,0","localRotation":"0,0,0","localScale":"1,1,1","left_x":52,"parentName":"bouncing","luaName":"RevivePointMark","param":""},{"localPosition":"53.77,1.53,0","localRotation":"0,0,0","localScale":"1,1,1","left_x":53,"parentName":"bouncing","luaName":"RhubarbDuckPointMark","param":""},{"trigger_localPosition":"-1.75,2.94,0","trigger_localRotation":"0,0,0","trigger_localScale":"1,1,1","trigger_size":"1,8,3","objects":[{"luaName":"KoffingEnemy","localPosition":"0.8300018,-5.1,0","localRotation":"0,90.00001,0","localScale":"1.2,1.2,-1.2","childLocalScale":"1,1,1","material_id":"15030000","path":[{"speed":40.0,"delay":0.0,"loopType":"none","easeType":"easeInOutSine","rotateAngle":"0,0,0","nodes":["0,0,0","0,5,0"]}]}],"localPosition":"59.19,1.1,0","localRotation":"0,0,0","localScale":"1,1,1","left_x":56,"parentName":"monster","luaName":"AnimTriggerItem","param":""},{"items":[{"localPosition":"-3.779,2.318,0","localRotation":"0,0,0","localScale":"-0.75,0.75,0.75","material_id":"15020000"},{"localPosition":"-6.426,-1.036,0","localRotation":"0,0,0","localScale":"-0.75,0.75,0.75","material_id":"15020000"},{"localPosition":"-1.154,-1.036,0","localRotation":"0,0,0","localScale":"-0.75,0.75,0.75","material_id":"15020000"},{"localPosition":"-6.27,-0.39,0","localRotation":"0,0,0","localScale":"-0.75,0.75,0.75","material_id":"15020000"},{"localPosition":"-1.3,-0.39,0","localRotation":"0,0,0","localScale":"-0.75,0.75,0.75","material_id":"15020000"},{"localPosition":"-6.01,0.25,0","localRotation":"0,0,0","localScale":"-0.75,0.75,0.75","material_id":"15020000"},{"localPosition":"-1.57,0.25,0","localRotation":"0,0,0","localScale":"-0.75,0.75,0.75","material_id":"15020000"},{"localPosition":"-5.63,0.89,0","localRotation":"0,0,0","localScale":"-0.75,0.75,0.75","material_id":"15020000"},{"localPosition":"-1.93,0.89,0","localRotation":"0,0,0","localScale":"-0.75,0.75,0.75","material_id":"15020000"},{"localPosition":"-5.16,1.54,0","localRotation":"0,0,0","localScale":"-0.75,0.75,0.75","material_id":"15020000"},{"localPosition":"-2.42,1.54,0","localRotation":"0,0,0","localScale":"-0.75,0.75,0.75","material_id":"15020000"},{"localPosition":"-4.5,2.02,0","localRotation":"0,0,0","localScale":"-0.75,0.75,0.75","material_id":"15020000"},{"localPosition":"-3.07,2.02,0","localRotation":"0,0,0","localScale":"-0.75,0.75,0.75","material_id":"15020000"}],"localPosition":"64,2,0","localRotation":"0,0,0","localScale":"1,1,1","left_x":57,"parentName":"item","luaName":"EliminateItemGroup","param":""},{"playerWallData_Right":{"playWallCount":-1,"isCanPlayWall":false,"stayTime":0.0,"acceleration":0.0},"playerWallData_Left":{"playWallCount":-1,"isCanPlayWall":false,"stayTime":0.0,"acceleration":0.0},"localPosition":"65,-3,0","localRotation":"0,0,0","localScale":"6,6,7","left_x":62,"parentName":"collider","luaName":"FlatSurface","param":""},{"localPosition":"62.71,0.59,0","localRotation":"0,0,0","localScale":"1,1,1","left_x":62,"parentName":"bouncing","luaName":"RevivePointMark","param":""},{"step_localPosition":"0,0.97,0","step_localScale":"3.5,0.4,6","bouncing_model_name":"jelly_blue","bouncing_model_localPosition":"0,0,0","bouncing_model_localRotation":"2.504478E-06,0,0","bouncing_model_localScale":"1.4,1.4,1.4","target_localPosition":"","bouncing_path":[{"speed":15.0,"delay":0.0,"loopType":"none","easeType":"easeOutExpo","rotateAngle":"0,0,0","nodes":["1.327209,1.004138,0","5.746185,0.3029639,0"]}],"localPosition":"73.72,-0.94,0","localRotation":"0,0,0","localScale":"1,1,1","left_x":71,"parentName":"bouncing","luaName":"BouncingSurface","param":"60;3;0;0;1","m_TargetZ":0.0,"m_isReplaceAction":1.0,"m_Direction":1.0,"m_ActionSpeed":1.0,"m_ActionDelayTime":0.0},{"step_localPosition":"0,1.13,0","step_localScale":"3.5,0.4,6","bouncing_model_name":"jelly_blue","bouncing_model_localPosition":"0,0,0","bouncing_model_localRotation":"2.504478E-06,0,0","bouncing_model_localScale":"1.4,1.4,1.4","target_localPosition":"","bouncing_path":[{"speed":15.0,"delay":0.0,"loopType":"none","easeType":"easeOutExpo","rotateAngle":"0,0,0","nodes":["1.281311,1.155931,0","6.189117,1.652575,0"]}],"localPosition":"77.5,-1.56,0","localRotation":"0,0,0","localScale":"1,1,1","left_x":75,"parentName":"bouncing","luaName":"BouncingSurface","param":"60;3;0;0;1","m_TargetZ":0.0,"m_isReplaceAction":1.0,"m_Direction":1.0,"m_ActionSpeed":1.0,"m_ActionDelayTime":0.0},{"localPosition":"76.81,0.54,0","localRotation":"0,0,0","localScale":"1,1,1","left_x":76,"parentName":"bouncing","luaName":"RhubarbDuckPointMark","param":""},{"step_localPosition":"0,1.16,0","step_localScale":"3.5,0.4,6","bouncing_model_name":"jelly_blue","bouncing_model_localPosition":"0,0,0","bouncing_model_localRotation":"2.504478E-06,0,0","bouncing_model_localScale":"1.4,1.4,1.4","target_localPosition":"","bouncing_path":[{"speed":20.0,"delay":0.0,"loopType":"none","easeType":"easeOutQuint","rotateAngle":"0,0,0","nodes":["0.4746933,1.729226,0","9.504555,9.391317,0","17.39134,0.9024799,0"]}],"localPosition":"81.62,-1.25,0","localRotation":"0,0,0","localScale":"1,1,1","left_x":79,"parentName":"bouncing","luaName":"BouncingSurface","param":"60;3;0","m_TargetZ":0.0,"m_isReplaceAction":1.0,"m_Direction":1.0,"m_ActionSpeed":1.0,"m_ActionDelayTime":0.0},{"localPosition":"80.71,0.67,0","localRotation":"0,0,0","localScale":"1,1,1","left_x":80,"parentName":"bouncing","luaName":"RevivePointMark","param":""},{"playerWallData_Right":{"playWallCount":-1,"isCanPlayWall":false,"stayTime":0.0,"acceleration":0.0},"playerWallData_Left":{"playWallCount":-1,"isCanPlayWall":false,"stayTime":0.0,"acceleration":0.0},"localPosition":"100,-3,0","localRotation":"0,0,0","localScale":"6,6,7","left_x":97,"parentName":"collider","luaName":"FlatSurface","param":""},{"localPosition":"97.95,0.67,0","localRotation":"0,0,0","localScale":"1,1,1","left_x":97,"parentName":"bouncing","luaName":"RevivePointMark","param":""},{"localPosition":"97.89261,0.7076573,0","localRotation":"0,0,0","localScale":"1,1,1","left_x":97,"parentName":"bouncing","luaName":"BouncingBlockItem","param":""},{"localPosition":"98.51,1.72,0","localRotation":"0,0,0","localScale":"1,1,1","left_x":98,"parentName":"bouncing","luaName":"RhubarbDuckPointMark","param":""},{"step_localPosition":"0,1.12,0","step_localScale":"3.5,0.4,6","bouncing_model_name":"jelly_blue","bouncing_model_localPosition":"0,0,0","bouncing_model_localRotation":"2.504478E-06,0,0","bouncing_model_localScale":"1.4,1.4,1.4","target_localPosition":"","bouncing_path":[{"speed":15.0,"delay":0.0,"loopType":"none","easeType":"easeOutExpo","rotateAngle":"0,0,0","nodes":["1.282372,1.098786,0","5.622955,0.1949682,0"]}],"localPosition":"108.75,-0.94,0","localRotation":"0,0,0","localScale":"1,1,1","left_x":106,"parentName":"bouncing","luaName":"BouncingSurface","param":"60;3;0;0;1","m_TargetZ":0.0,"m_isReplaceAction":1.0,"m_Direction":1.0,"m_ActionSpeed":1.0,"m_ActionDelayTime":0.0},{"step_localPosition":"0,1.14,0","step_localScale":"3.5,0.4,6","bouncing_model_name":"jelly_blue","bouncing_model_localPosition":"0,0,0","bouncing_model_localRotation":"2.504478E-06,0,0","bouncing_model_localScale":"1.4,1.4,1.4","target_localPosition":"","bouncing_path":[{"speed":15.0,"delay":0.0,"loopType":"none","easeType":"easeOutExpo","rotateAngle":"0,0,0","nodes":["1.256569,1.188938,0","6.024887,1.66883,0"]}],"localPosition":"112.53,-1.56,0","localRotation":"0,0,0","localScale":"1,1,1","left_x":110,"parentName":"bouncing","luaName":"BouncingSurface","param":"60;3;0;0;1","m_TargetZ":0.0,"m_isReplaceAction":1.0,"m_Direction":1.0,"m_ActionSpeed":1.0,"m_ActionDelayTime":0.0},{"localPosition":"112.15,0.74,0","localRotation":"0,0,0","localScale":"1,1,1","left_x":111,"parentName":"bouncing","luaName":"RhubarbDuckPointMark","param":""},{"step_localPosition":"0,1.16,0","step_localScale":"3.5,0.4,6","bouncing_model_name":"jelly_blue","bouncing_model_localPosition":"0,0,0","bouncing_model_localRotation":"2.504478E-06,0,0","bouncing_model_localScale":"1.4,1.4,1.4","target_localPosition":"","bouncing_path":[{"speed":20.0,"delay":0.0,"loopType":"none","easeType":"easeOutQuint","rotateAngle":"0,0,0","nodes":["0.4746933,1.729226,0","9.03968,8.817083,0","17.39135,0.9024799,0"]}],"localPosition":"116.65,-1.25,0","localRotation":"0,0,0","localScale":"1,1,1","left_x":114,"parentName":"bouncing","luaName":"BouncingSurface","param":"60;3;0","m_TargetZ":0.0,"m_isReplaceAction":1.0,"m_Direction":1.0,"m_ActionSpeed":1.0,"m_ActionDelayTime":0.0},{"localPosition":"115.78,0.61,0","localRotation":"0,0,0","localScale":"1,1,1","left_x":115,"parentName":"bouncing","luaName":"RevivePointMark","param":""},{"playerWallData_Right":{"playWallCount":-1,"isCanPlayWall":false,"stayTime":0.0,"acceleration":0.0},"playerWallData_Left":{"playWallCount":-1,"isCanPlayWall":false,"stayTime":0.0,"acceleration":0.0},"localPosition":"163,-3,0","localRotation":"0,0,0","localScale":"64,6,7","left_x":131,"parentName":"collider","luaName":"FlatSurface","param":""},{"localPosition":"132.48,0.67,0","localRotation":"0,0,0","localScale":"1,1,1","left_x":131,"parentName":"bouncing","luaName":"RevivePointMark","param":""},{"localPosition":"132.92,0.71,0","localRotation":"0,0,0","localScale":"1,1,1","left_x":132,"parentName":"bouncing","luaName":"BouncingBlockItem","param":""},{"localPosition":"134.25,3.23,0","localRotation":"0,0,0","localScale":"1,1,1","left_x":133,"parentName":"bouncing","luaName":"RhubarbDuckPointMark","param":""},{"localPosition":"134.69,0.63,0","localRotation":"0,0,0","localScale":"1,1,1","left_x":134,"parentName":"bouncing","luaName":"HolyLandingPointMark","param":""},{"items":[{"localPosition":"-0.23,-2.39,0","localRotation":"0,0,0","localScale":"2.5,2.5,2.5","material_id":"15123000"},{"localPosition":"0.6829834,-0.5185671,0","localRotation":"0,0,0","localScale":"1,1,1","material_id":"15124000"},{"localPosition":"1.482986,-1.128567,0","localRotation":"0,0,0","localScale":"1,1,1","material_id":"15124000"},{"localPosition":"1.922989,-2.048567,0","localRotation":"0,0,0","localScale":"1,1,1","material_id":"15124000"},{"localPosition":"1.942978,-3.098567,0","localRotation":"0,0,0","localScale":"1,1,1","material_id":"15124000"},{"localPosition":"1.442978,-3.978567,0","localRotation":"0,0,0","localScale":"1,1,1","material_id":"15124000"},{"localPosition":"0.4629822,-4.378567,0","localRotation":"0,0,0","localScale":"1,1,1","material_id":"15124000"},{"localPosition":"-0.5570221,-4.528567,0","localRotation":"0,0,0","localScale":"1,1,1","material_id":"15124000"},{"localPosition":"-1.517014,-4.038568,0","localRotation":"0,0,0","localScale":"1,1,1","material_id":"15124000"},{"localPosition":"-2.257019,-3.238567,0","localRotation":"0,0,0","localScale":"1,1,1","material_id":"15124000"},{"localPosition":"-2.257019,-3.238567,0","localRotation":"0,0,0","localScale":"1,1,1","material_id":"15124000"},{"localPosition":"-2.317017,-2.188567,0","localRotation":"0,0,0","localScale":"1,1,1","material_id":"15124000"},{"localPosition":"-2.007019,-1.358567,0","localRotation":"0,0,0","localScale":"1,1,1","material_id":"15124000"},{"localPosition":"-1.327011,-0.6185675,0","localRotation":"0,0,0","localScale":"1,1,1","material_id":"15124000"},{"localPosition":"-0.3413696,-0.2776666,0","localRotation":"0,0,0","localScale":"1,1,1","material_id":"15124000"}],"localPosition":"142.69,6,0","localRotation":"0,0,0","localScale":"1,1,1","left_x":139,"parentName":"item","luaName":"EliminateItemGroup","param":""},{"items":[{"localPosition":"0,0,0","localRotation":"0,0,0","localScale":"-0.75,0.75,0.75","material_id":"15020000"},{"localPosition":"0.5,-0.5,0","localRotation":"0,0,0","localScale":"-0.75,0.75,0.75","material_id":"15020000"},{"localPosition":"1,-1,0","localRotation":"0,0,0","localScale":"-0.75,0.75,0.75","material_id":"15020000"},{"localPosition":"1.5,-1.5,0","localRotation":"0,0,0","localScale":"-0.75,0.75,0.75","material_id":"15020000"},{"localPosition":"2,-2,0","localRotation":"0,0,0","localScale":"-0.75,0.75,0.75","material_id":"15020000"},{"localPosition":"2.5,-1.5,0","localRotation":"0,0,0","localScale":"-0.75,0.75,0.75","material_id":"15020000"},{"localPosition":"3,-1,0","localRotation":"0,0,0","localScale":"-0.75,0.75,0.75","material_id":"15020000"},{"localPosition":"3.5,-0.5,0","localRotation":"0,0,0","localScale":"-0.75,0.75,0.75","material_id":"15020000"},{"localPosition":"4,0,0","localRotation":"0,0,0","localScale":"-0.75,0.75,0.75","material_id":"15020000"},{"localPosition":"4.5,-0.5,0","localRotation":"0,0,0","localScale":"-0.75,0.75,0.75","material_id":"15020000"},{"localPosition":"5,-1,0","localRotation":"0,0,0","localScale":"-0.75,0.75,0.75","material_id":"15020000"},{"localPosition":"5.5,-1.5,0","localRotation":"0,0,0","localScale":"-0.75,0.75,0.75","material_id":"15020000"},{"localPosition":"6,-2,0","localRotation":"0,0,0","localScale":"-0.75,0.75,0.75","material_id":"15020000"},{"localPosition":"6.5,-1.5,0","localRotation":"0,0,0","localScale":"-0.75,0.75,0.75","material_id":"15020000"},{"localPosition":"7,-1,0","localRotation":"0,0,0","localScale":"-0.75,0.75,0.75","material_id":"15020000"},{"localPosition":"7.5,-0.5,0","localRotation":"0,0,0","localScale":"-0.75,0.75,0.75","material_id":"15020000"},{"localPosition":"8,0,0","localRotation":"0,0,0","localScale":"-0.75,0.75,0.75","material_id":"15020000"},{"localPosition":"8.5,-0.5,0","localRotation":"0,0,0","localScale":"-0.75,0.75,0.75","material_id":"15020000"},{"localPosition":"9,-1,0","localRotation":"0,0,0","localScale":"-0.75,0.75,0.75","material_id":"15020000"},{"localPosition":"9.5,-1.5,0","localRotation":"0,0,0","localScale":"-0.75,0.75,0.75","material_id":"15020000"},{"localPosition":"10,-2,0","localRotation":"0,0,0","localScale":"-0.75,0.75,0.75","material_id":"15020000"},{"localPosition":"10.5,-1.5,0","localRotation":"0,0,0","localScale":"-0.75,0.75,0.75","material_id":"15020000"},{"localPosition":"11,-1,0","localRotation":"0,0,0","localScale":"-0.75,0.75,0.75","material_id":"15020000"},{"localPosition":"11.5,-0.5,0","localRotation":"0,0,0","localScale":"-0.75,0.75,0.75","material_id":"15020000"},{"localPosition":"12,0,0","localRotation":"0,0,0","localScale":"-0.75,0.75,0.75","material_id":"15020000"},{"localPosition":"4.71,-1.97,0","localRotation":"0,0,0","localScale":"1,1,1","material_id":"15001000"},{"localPosition":"3.27,-1.98,0","localRotation":"0,0,0","localScale":"1,1,1","material_id":"15001000"},{"localPosition":"8.024,-1.2,0","localRotation":"0,0,0","localScale":"1,1,1","material_id":"15001000"},{"localPosition":"4.024,-1.2,0","localRotation":"0,0,0","localScale":"1,1,1","material_id":"15001000"},{"localPosition":"7.27,-1.97,0","localRotation":"0,0,0","localScale":"1,1,1","material_id":"15001000"},{"localPosition":"8.74,-1.94,0","localRotation":"0,0,0","localScale":"1,1,1","material_id":"15001000"},{"localPosition":"1.447,-2.562,0","localRotation":"0,0,0","localScale":"1,1,1","material_id":"15021000"},{"localPosition":"0.729,-3.3,0","localRotation":"0,0,0","localScale":"1,1,1","material_id":"15021000"},{"localPosition":"0,-4,0","localRotation":"0,0,0","localScale":"1,1,1","material_id":"15021000"},{"localPosition":"2.53,-2.58,0","localRotation":"0,0,0","localScale":"1,1,1","material_id":"15021000"},{"localPosition":"3.26,-3.3,0","localRotation":"0,0,0","localScale":"1,1,1","material_id":"15021000"},{"localPosition":"4,-4,0","localRotation":"0,0,0","localScale":"1,1,1","material_id":"15021000"},{"localPosition":"4.718,-3.3,0","localRotation":"0,0,0","localScale":"1,1,1","material_id":"15021000"},{"localPosition":"5.473,-2.62,0","localRotation":"0,0,0","localScale":"1,1,1","material_id":"15021000"},{"localPosition":"6.57,-2.64,0","localRotation":"0,0,0","localScale":"1,1,1","material_id":"15021000"},{"localPosition":"7.31,-3.3,0","localRotation":"0,0,0","localScale":"1,1,1","material_id":"15021000"},{"localPosition":"8.03,-4,0","localRotation":"0,0,0","localScale":"1,1,1","material_id":"15021000"},{"localPosition":"8.795,-3.3,0","localRotation":"0,0,0","localScale":"1,1,1","material_id":"15021000"},{"localPosition":"9.488,-2.624,0","localRotation":"0,0,0","localScale":"1,1,1","material_id":"15021000"},{"localPosition":"10.525,-2.635,0","localRotation":"0,0,0","localScale":"1,1,1","material_id":"15021000"},{"localPosition":"11.194,-3.3,0","localRotation":"0,0,0","localScale":"1,1,1","material_id":"15021000"},{"localPosition":"11.91,-4,0","localRotation":"0,0,0","localScale":"1,1,1","material_id":"15021000"},{"localPosition":"4,-2.68,0","localRotation":"0,0,0","localScale":"1,1,1","material_id":"15001000"},{"localPosition":"8.04,-2.69,0","localRotation":"0,0,0","localScale":"1,1,1","material_id":"15001000"}],"localPosition":"145.67,5.74,0","localRotation":"0,0,0","localScale":"1,1,1","left_x":145,"parentName":"item","luaName":"EliminateItemGroup","param":""},{"localPosition":"150.8,1.8,0","localRotation":"0,0,0","localScale":"1,1,1","left_x":150,"parentName":"bouncing","luaName":"RhubarbDuckPointMark","param":""},{"items":[{"localPosition":"-0.23,-2.39,0","localRotation":"0,0,0","localScale":"2.5,2.5,2.5","material_id":"15123000"},{"localPosition":"0.6829834,-0.5185671,0","localRotation":"0,0,0","localScale":"1,1,1","material_id":"15124000"},{"localPosition":"1.482986,-1.128567,0","localRotation":"0,0,0","localScale":"1,1,1","material_id":"15124000"},{"localPosition":"1.922989,-2.048567,0","localRotation":"0,0,0","localScale":"1,1,1","material_id":"15124000"},{"localPosition":"1.942978,-3.098567,0","localRotation":"0,0,0","localScale":"1,1,1","material_id":"15124000"},{"localPosition":"1.442978,-3.978567,0","localRotation":"0,0,0","localScale":"1,1,1","material_id":"15124000"},{"localPosition":"0.4629822,-4.378567,0","localRotation":"0,0,0","localScale":"1,1,1","material_id":"15124000"},{"localPosition":"-0.5570221,-4.528567,0","localRotation":"0,0,0","localScale":"1,1,1","material_id":"15124000"},{"localPosition":"-1.517014,-4.038568,0","localRotation":"0,0,0","localScale":"1,1,1","material_id":"15124000"},{"localPosition":"-2.257019,-3.238567,0","localRotation":"0,0,0","localScale":"1,1,1","material_id":"15124000"},{"localPosition":"-2.257019,-3.238567,0","localRotation":"0,0,0","localScale":"1,1,1","material_id":"15124000"},{"localPosition":"-2.317017,-2.188567,0","localRotation":"0,0,0","localScale":"1,1,1","material_id":"15124000"},{"localPosition":"-2.007019,-1.358567,0","localRotation":"0,0,0","localScale":"1,1,1","material_id":"15124000"},{"localPosition":"-1.327011,-0.6185675,0","localRotation":"0,0,0","localScale":"1,1,1","material_id":"15124000"},{"localPosition":"-0.3413696,-0.2776666,0","localRotation":"0,0,0","localScale":"1,1,1","material_id":"15124000"}],"localPosition":"160.99,6,0","localRotation":"0,0,0","localScale":"1,1,1","left_x":158,"parentName":"item","luaName":"EliminateItemGroup","param":""},{"localPosition":"163.63,1.2,0","localRotation":"0,0,0","localScale":"1,1,1","left_x":163,"parentName":"bouncing","luaName":"RhubarbDuckPointMark","param":""},{"localPosition":"165.72,3.3,0","localRotation":"0,270,0","localScale":"1,1,-1","left_x":165,"parentName":"item","luaName":"StaminaBottle","param":"15035000"},{"items":[{"localPosition":"-0.23,-2.39,0","localRotation":"0,0,0","localScale":"2.5,2.5,2.5","material_id":"15123000"},{"localPosition":"0.6829834,-0.5185671,0","localRotation":"0,0,0","localScale":"1,1,1","material_id":"15124000"},{"localPosition":"1.482986,-1.128567,0","localRotation":"0,0,0","localScale":"1,1,1","material_id":"15124000"},{"localPosition":"1.922989,-2.048567,0","localRotation":"0,0,0","localScale":"1,1,1","material_id":"15124000"},{"localPosition":"1.942978,-3.098567,0","localRotation":"0,0,0","localScale":"1,1,1","material_id":"15124000"},{"localPosition":"1.442978,-3.978567,0","localRotation":"0,0,0","localScale":"1,1,1","material_id":"15124000"},{"localPosition":"0.4629822,-4.378567,0","localRotation":"0,0,0","localScale":"1,1,1","material_id":"15124000"},{"localPosition":"-0.5570221,-4.528567,0","localRotation":"0,0,0","localScale":"1,1,1","material_id":"15124000"},{"localPosition":"-1.517014,-4.038568,0","localRotation":"0,0,0","localScale":"1,1,1","material_id":"15124000"},{"localPosition":"-2.257019,-3.238567,0","localRotation":"0,0,0","localScale":"1,1,1","material_id":"15124000"},{"localPosition":"-2.257019,-3.238567,0","localRotation":"0,0,0","localScale":"1,1,1","material_id":"15124000"},{"localPosition":"-2.317017,-2.188567,0","localRotation":"0,0,0","localScale":"1,1,1","material_id":"15124000"},{"localPosition":"-2.007019,-1.358567,0","localRotation":"0,0,0","localScale":"1,1,1","material_id":"15124000"},{"localPosition":"-1.327011,-0.6185675,0","localRotation":"0,0,0","localScale":"1,1,1","material_id":"15124000"},{"localPosition":"-0.3413696,-0.2776666,0","localRotation":"0,0,0","localScale":"1,1,1","material_id":"15124000"}],"localPosition":"170.72,6,0","localRotation":"0,0,0","localScale":"1,1,1","left_x":167,"parentName":"item","luaName":"EliminateItemGroup","param":""},{"localPosition":"167.91,0.63,0","localRotation":"0,0,0","localScale":"1,1,1","left_x":167,"parentName":"bouncing","luaName":"HolyLandingPointMark","param":""},{"items":[{"localPosition":"0,0,0","localRotation":"0,0,0","localScale":"-0.75,0.75,0.75","material_id":"15020000"},{"localPosition":"0.5,-0.5,0","localRotation":"0,0,0","localScale":"-0.75,0.75,0.75","material_id":"15020000"},{"localPosition":"1,-1,0","localRotation":"0,0,0","localScale":"-0.75,0.75,0.75","material_id":"15020000"},{"localPosition":"1.5,-1.5,0","localRotation":"0,0,0","localScale":"-0.75,0.75,0.75","material_id":"15020000"},{"localPosition":"2,-2,0","localRotation":"0,0,0","localScale":"-0.75,0.75,0.75","material_id":"15020000"},{"localPosition":"2.5,-1.5,0","localRotation":"0,0,0","localScale":"-0.75,0.75,0.75","material_id":"15020000"},{"localPosition":"3,-1,0","localRotation":"0,0,0","localScale":"-0.75,0.75,0.75","material_id":"15020000"},{"localPosition":"3.5,-0.5,0","localRotation":"0,0,0","localScale":"-0.75,0.75,0.75","material_id":"15020000"},{"localPosition":"4,0,0","localRotation":"0,0,0","localScale":"-0.75,0.75,0.75","material_id":"15020000"},{"localPosition":"4.5,-0.5,0","localRotation":"0,0,0","localScale":"-0.75,0.75,0.75","material_id":"15020000"},{"localPosition":"5,-1,0","localRotation":"0,0,0","localScale":"-0.75,0.75,0.75","material_id":"15020000"},{"localPosition":"5.5,-1.5,0","localRotation":"0,0,0","localScale":"-0.75,0.75,0.75","material_id":"15020000"},{"localPosition":"6,-2,0","localRotation":"0,0,0","localScale":"-0.75,0.75,0.75","material_id":"15020000"},{"localPosition":"6.5,-1.5,0","localRotation":"0,0,0","localScale":"-0.75,0.75,0.75","material_id":"15020000"},{"localPosition":"7,-1,0","localRotation":"0,0,0","localScale":"-0.75,0.75,0.75","material_id":"15020000"},{"localPosition":"7.5,-0.5,0","localRotation":"0,0,0","localScale":"-0.75,0.75,0.75","material_id":"15020000"},{"localPosition":"8,0,0","localRotation":"0,0,0","localScale":"-0.75,0.75,0.75","material_id":"15020000"},{"localPosition":"8.5,-0.5,0","localRotation":"0,0,0","localScale":"-0.75,0.75,0.75","material_id":"15020000"},{"localPosition":"9,-1,0","localRotation":"0,0,0","localScale":"-0.75,0.75,0.75","material_id":"15020000"},{"localPosition":"9.5,-1.5,0","localRotation":"0,0,0","localScale":"-0.75,0.75,0.75","material_id":"15020000"},{"localPosition":"10,-2,0","localRotation":"0,0,0","localScale":"-0.75,0.75,0.75","material_id":"15020000"},{"localPosition":"10.5,-1.5,0","localRotation":"0,0,0","localScale":"-0.75,0.75,0.75","material_id":"15020000"},{"localPosition":"11,-1,0","localRotation":"0,0,0","localScale":"-0.75,0.75,0.75","material_id":"15020000"},{"localPosition":"11.5,-0.5,0","localRotation":"0,0,0","localScale":"-0.75,0.75,0.75","material_id":"15020000"},{"localPosition":"12,0,0","localRotation":"0,0,0","localScale":"-0.75,0.75,0.75","material_id":"15020000"},{"localPosition":"4.71,-1.97,0","localRotation":"0,0,0","localScale":"1,1,1","material_id":"15001000"},{"localPosition":"3.27,-1.98,0","localRotation":"0,0,0","localScale":"1,1,1","material_id":"15001000"},{"localPosition":"8.024,-1.2,0","localRotation":"0,0,0","localScale":"1,1,1","material_id":"15001000"},{"localPosition":"4.024,-1.2,0","localRotation":"0,0,0","localScale":"1,1,1","material_id":"15001000"},{"localPosition":"7.27,-1.97,0","localRotation":"0,0,0","localScale":"1,1,1","material_id":"15001000"},{"localPosition":"8.74,-1.94,0","localRotation":"0,0,0","localScale":"1,1,1","material_id":"15001000"},{"localPosition":"1.447,-2.562,0","localRotation":"0,0,0","localScale":"1,1,1","material_id":"15021000"},{"localPosition":"0.729,-3.3,0","localRotation":"0,0,0","localScale":"1,1,1","material_id":"15021000"},{"localPosition":"0,-4,0","localRotation":"0,0,0","localScale":"1,1,1","material_id":"15021000"},{"localPosition":"2.53,-2.58,0","localRotation":"0,0,0","localScale":"1,1,1","material_id":"15021000"},{"localPosition":"3.26,-3.3,0","localRotation":"0,0,0","localScale":"1,1,1","material_id":"15021000"},{"localPosition":"4,-4,0","localRotation":"0,0,0","localScale":"1,1,1","material_id":"15021000"},{"localPosition":"4.718,-3.3,0","localRotation":"0,0,0","localScale":"1,1,1","material_id":"15021000"},{"localPosition":"5.473,-2.62,0","localRotation":"0,0,0","localScale":"1,1,1","material_id":"15021000"},{"localPosition":"6.57,-2.64,0","localRotation":"0,0,0","localScale":"1,1,1","material_id":"15021000"},{"localPosition":"7.31,-3.3,0","localRotation":"0,0,0","localScale":"1,1,1","material_id":"15021000"},{"localPosition":"8.03,-4,0","localRotation":"0,0,0","localScale":"1,1,1","material_id":"15021000"},{"localPosition":"8.795,-3.3,0","localRotation":"0,0,0","localScale":"1,1,1","material_id":"15021000"},{"localPosition":"9.488,-2.624,0","localRotation":"0,0,0","localScale":"1,1,1","material_id":"15021000"},{"localPosition":"10.525,-2.635,0","localRotation":"0,0,0","localScale":"1,1,1","material_id":"15021000"},{"localPosition":"11.194,-3.3,0","localRotation":"0,0,0","localScale":"1,1,1","material_id":"15021000"},{"localPosition":"11.91,-4,0","localRotation":"0,0,0","localScale":"1,1,1","material_id":"15021000"},{"localPosition":"4,-2.68,0","localRotation":"0,0,0","localScale":"1,1,1","material_id":"15001000"},{"localPosition":"8.04,-2.69,0","localRotation":"0,0,0","localScale":"1,1,1","material_id":"15001000"}],"localPosition":"173.7,5.74,0","localRotation":"0,0,0","localScale":"1,1,1","left_x":173,"parentName":"item","luaName":"EliminateItemGroup","param":""},{"localPosition":"179.76,1.99,0","localRotation":"0,0,0","localScale":"1,1,1","left_x":179,"parentName":"bouncing","luaName":"RhubarbDuckPointMark","param":""},{"items":[{"localPosition":"-0.23,-2.39,0","localRotation":"0,0,0","localScale":"2.5,2.5,2.5","material_id":"15123000"},{"localPosition":"0.6829834,-0.5185671,0","localRotation":"0,0,0","localScale":"1,1,1","material_id":"15124000"},{"localPosition":"1.482986,-1.128567,0","localRotation":"0,0,0","localScale":"1,1,1","material_id":"15124000"},{"localPosition":"1.922989,-2.048567,0","localRotation":"0,0,0","localScale":"1,1,1","material_id":"15124000"},{"localPosition":"1.942978,-3.098567,0","localRotation":"0,0,0","localScale":"1,1,1","material_id":"15124000"},{"localPosition":"1.442978,-3.978567,0","localRotation":"0,0,0","localScale":"1,1,1","material_id":"15124000"},{"localPosition":"0.4629822,-4.378567,0","localRotation":"0,0,0","localScale":"1,1,1","material_id":"15124000"},{"localPosition":"-0.5570221,-4.528567,0","localRotation":"0,0,0","localScale":"1,1,1","material_id":"15124000"},{"localPosition":"-1.517014,-4.038568,0","localRotation":"0,0,0","localScale":"1,1,1","material_id":"15124000"},{"localPosition":"-2.257019,-3.238567,0","localRotation":"0,0,0","localScale":"1,1,1","material_id":"15124000"},{"localPosition":"-2.257019,-3.238567,0","localRotation":"0,0,0","localScale":"1,1,1","material_id":"15124000"},{"localPosition":"-2.317017,-2.188567,0","localRotation":"0,0,0","localScale":"1,1,1","material_id":"15124000"},{"localPosition":"-2.007019,-1.358567,0","localRotation":"0,0,0","localScale":"1,1,1","material_id":"15124000"},{"localPosition":"-1.327011,-0.6185675,0","localRotation":"0,0,0","localScale":"1,1,1","material_id":"15124000"},{"localPosition":"-0.3413696,-0.2776666,0","localRotation":"0,0,0","localScale":"1,1,1","material_id":"15124000"}],"localPosition":"189.02,6,0","localRotation":"0,0,0","localScale":"1,1,1","left_x":186,"parentName":"item","luaName":"EliminateItemGroup","param":""},{"localPosition":"191.96,2.38,0","localRotation":"0,0,0","localScale":"1,1,1","left_x":191,"parentName":"bouncing","luaName":"RhubarbDuckPointMark","param":""}]