[{"playerWallData_Right":{"playWallCount":-1,"isCanPlayWall":false,"stayTime":0.0,"acceleration":0.0},"playerWallData_Left":{"playWallCount":-1,"isCanPlayWall":false,"stayTime":0.0,"acceleration":0.0},"localPosition":"8,-3,0","localRotation":"0,0,0","localScale":"16,6,7","left_x":0,"parentName":"collider","luaName":"FlatSurface","param":""},{"surface_localScale":"283,0.1,100","target_localPosition":null,"localPosition":"141.5,-6.1,0","localRotation":"0,0,0","localScale":"1,1,1","left_x":0,"parentName":"revive","luaName":"ReviveSurface","param":"10"},{"localPosition":"5.05,2.25,0","localRotation":"0,0,0","localScale":"1,1,1","left_x":4,"parentName":"bouncing","luaName":"RhubarbDuckPointMark","param":""},{"localPosition":"4.98,0.56,0","localRotation":"0,0,0","localScale":"1,1,1","left_x":4,"parentName":"bouncing","luaName":"RevivePointMark","param":""},{"items":[{"localPosition":"-1.636,0,0","localRotation":"0,0,0","localScale":"-0.75,0.75,0.75","material_id":"15020000"},{"localPosition":"-0.815,0,0","localRotation":"0,0,0","localScale":"-0.75,0.75,0.75","material_id":"15020000"},{"localPosition":"0,0,0","localRotation":"0,0,0","localScale":"-0.75,0.75,0.75","material_id":"15020000"},{"localPosition":"0.829,0,0","localRotation":"0,0,0","localScale":"-0.75,0.75,0.75","material_id":"15020000"},{"localPosition":"1.643,0,0","localRotation":"0,0,0","localScale":"-0.75,0.75,0.75","material_id":"15020000"}],"localPosition":"13.074,1.096,0","localRotation":"0,0,0","localScale":"1,1,1","left_x":10,"parentName":"item","luaName":"EliminateItemGroup","param":""},{"items":[{"localPosition":"-3.779,2.318,0","localRotation":"0,0,0","localScale":"-0.75,0.75,0.75","material_id":"15020000"},{"localPosition":"-6.426,-1.036,0","localRotation":"0,0,0","localScale":"-0.75,0.75,0.75","material_id":"15020000"},{"localPosition":"-0.934,-1.079,0","localRotation":"0,0,0","localScale":"-0.75,0.75,0.75","material_id":"15020000"},{"localPosition":"-6.27,-0.39,0","localRotation":"0,0,0","localScale":"-0.75,0.75,0.75","material_id":"15020000"},{"localPosition":"-1.233,-0.39,0","localRotation":"0,0,0","localScale":"-0.75,0.75,0.75","material_id":"15020000"},{"localPosition":"-6.01,0.25,0","localRotation":"0,0,0","localScale":"-0.75,0.75,0.75","material_id":"15020000"},{"localPosition":"-1.57,0.25,0","localRotation":"0,0,0","localScale":"-0.75,0.75,0.75","material_id":"15020000"},{"localPosition":"-5.63,0.89,0","localRotation":"0,0,0","localScale":"-0.75,0.75,0.75","material_id":"15020000"},{"localPosition":"-1.93,0.89,0","localRotation":"0,0,0","localScale":"-0.75,0.75,0.75","material_id":"15020000"},{"localPosition":"-5.16,1.54,0","localRotation":"0,0,0","localScale":"-0.75,0.75,0.75","material_id":"15020000"},{"localPosition":"-2.42,1.54,0","localRotation":"0,0,0","localScale":"-0.75,0.75,0.75","material_id":"15020000"},{"localPosition":"-4.5,2.02,0","localRotation":"0,0,0","localScale":"-0.75,0.75,0.75","material_id":"15020000"},{"localPosition":"-3.07,2.02,0","localRotation":"0,0,0","localScale":"-0.75,0.75,0.75","material_id":"15020000"},{"localPosition":"-0.662,-1.8,0","localRotation":"0,0,0","localScale":"-0.75,0.75,0.75","material_id":"15020000"},{"localPosition":"-0.39,-2.77,0","localRotation":"0,0,0","localScale":"-0.75,0.75,0.75","material_id":"15020000"}],"localPosition":"22,2.16,0","localRotation":"0,0,0","localScale":"1,1,1","left_x":15,"parentName":"item","luaName":"EliminateItemGroup","param":""},{"collider_center":null,"collider_radius":null,"collider_height":null,"localPosition":"18,0,0","localRotation":"0,90.00001,0","localScale":"1.2,1.2,-1.2","left_x":17,"parentName":"monster","luaName":"KoffingEnemy","param":"15030000"},{"playerWallData_Right":{"playWallCount":-1,"isCanPlayWall":false,"stayTime":0.0,"acceleration":0.0},"playerWallData_Left":{"playWallCount":-1,"isCanPlayWall":false,"stayTime":0.0,"acceleration":0.0},"localPosition":"24,-4,0","localRotation":"0,0,0","localScale":"8,4,7","left_x":20,"parentName":"collider","luaName":"FlatSurface","param":""},{"localPosition":"20.93,-1.41,0","localRotation":"0,0,0","localScale":"1,1,1","left_x":20,"parentName":"bouncing","luaName":"RevivePointMark","param":""},{"collider_center":null,"collider_radius":null,"collider_height":null,"localPosition":"22.67,3,0","localRotation":"0,90.00001,0","localScale":"1.2,1.2,-1.2","left_x":22,"parentName":"monster","luaName":"KoffingEnemy","param":"15030000"},{"items":[{"localPosition":"-3.779,2.318,0","localRotation":"0,0,0","localScale":"-0.75,0.75,0.75","material_id":"15020000"},{"localPosition":"-6.426,-1.036,0","localRotation":"0,0,0","localScale":"-0.75,0.75,0.75","material_id":"15020000"},{"localPosition":"-6.27,-0.39,0","localRotation":"0,0,0","localScale":"-0.75,0.75,0.75","material_id":"15020000"},{"localPosition":"-6.01,0.25,0","localRotation":"0,0,0","localScale":"-0.75,0.75,0.75","material_id":"15020000"},{"localPosition":"-5.63,0.89,0","localRotation":"0,0,0","localScale":"-0.75,0.75,0.75","material_id":"15020000"},{"localPosition":"-1.93,0.89,0","localRotation":"0,0,0","localScale":"-0.75,0.75,0.75","material_id":"15020000"},{"localPosition":"-5.16,1.54,0","localRotation":"0,0,0","localScale":"-0.75,0.75,0.75","material_id":"15020000"},{"localPosition":"-2.42,1.54,0","localRotation":"0,0,0","localScale":"-0.75,0.75,0.75","material_id":"15020000"},{"localPosition":"-4.5,2.02,0","localRotation":"0,0,0","localScale":"-0.75,0.75,0.75","material_id":"15020000"},{"localPosition":"-3.07,2.02,0","localRotation":"0,0,0","localScale":"-0.75,0.75,0.75","material_id":"15020000"}],"localPosition":"31.32,0.42,0","localRotation":"0,0,0","localScale":"1,1,1","left_x":24,"parentName":"item","luaName":"EliminateItemGroup","param":""},{"collider_center":null,"collider_radius":null,"collider_height":null,"localPosition":"27,-1,0","localRotation":"0,90.00001,0","localScale":"1.2,1.2,-1.2","left_x":26,"parentName":"monster","luaName":"KoffingEnemy","param":"15030000"},{"playerWallData_Right":{"playWallCount":-1,"isCanPlayWall":false,"stayTime":0.0,"acceleration":0.0},"playerWallData_Left":{"playWallCount":-1,"isCanPlayWall":false,"stayTime":0.0,"acceleration":0.0},"localPosition":"34,-3,0","localRotation":"0,0,0","localScale":"12,6,7","left_x":28,"parentName":"collider","luaName":"FlatSurface","param":""},{"localPosition":"29.12,0.63,0","localRotation":"0,0,0","localScale":"1,1,1","left_x":28,"parentName":"bouncing","luaName":"HolyLandingPointMark","param":""},{"localPosition":"32.02,0.98,0","localRotation":"0,0,0","localScale":"1,1,1","left_x":31,"parentName":"bouncing","luaName":"RhubarbDuckPointMark","param":""},{"collider_center":null,"collider_radius":null,"collider_height":null,"localPosition":"34.51455,0,0","localRotation":"0,0,0","localScale":"1.5,1.5,-1.5","left_x":33,"parentName":"monster","luaName":"SlideMoleEnemy","param":"15106000"},{"trigger_localPosition":"-5.05,3,0","trigger_localRotation":"0,0,0","trigger_localScale":"1,1,1","trigger_size":"1,8,3","objects":[{"luaName":"KoffingEnemy","localPosition":"0,0,0","localRotation":"0,90.00001,0","localScale":"1.2,1.2,-1.2","childLocalScale":"1,1,1","material_id":"15030000","path":[{"speed":30.0,"delay":0.0,"loopType":"none","easeType":"easeInOutSine","rotateAngle":"0,0,0","nodes":["0,0,0","0,-4,0","0,0,0"]}]}],"localPosition":"41.5,1,0","localRotation":"0,0,0","localScale":"1,1,1","left_x":35,"parentName":"monster","luaName":"AnimTriggerItem","param":""},{"items":[{"localPosition":"-3.779,2.318,0","localRotation":"0,0,0","localScale":"-0.75,0.75,0.75","material_id":"15020000"},{"localPosition":"-6.426,-1.036,0","localRotation":"0,0,0","localScale":"-0.75,0.75,0.75","material_id":"15020000"},{"localPosition":"-6.27,-0.39,0","localRotation":"0,0,0","localScale":"-0.75,0.75,0.75","material_id":"15020000"},{"localPosition":"-6.01,0.25,0","localRotation":"0,0,0","localScale":"-0.75,0.75,0.75","material_id":"15020000"},{"localPosition":"-5.63,0.89,0","localRotation":"0,0,0","localScale":"-0.75,0.75,0.75","material_id":"15020000"},{"localPosition":"-1.93,0.89,0","localRotation":"0,0,0","localScale":"-0.75,0.75,0.75","material_id":"15020000"},{"localPosition":"-5.16,1.54,0","localRotation":"0,0,0","localScale":"-0.75,0.75,0.75","material_id":"15020000"},{"localPosition":"-2.42,1.54,0","localRotation":"0,0,0","localScale":"-0.75,0.75,0.75","material_id":"15020000"},{"localPosition":"-4.5,2.02,0","localRotation":"0,0,0","localScale":"-0.75,0.75,0.75","material_id":"15020000"},{"localPosition":"-3.07,2.02,0","localRotation":"0,0,0","localScale":"-0.75,0.75,0.75","material_id":"15020000"}],"localPosition":"45.8,2.382,0","localRotation":"0,0,0","localScale":"1,1,1","left_x":38,"parentName":"item","luaName":"EliminateItemGroup","param":""},{"playerWallData_Right":{"playWallCount":-1,"isCanPlayWall":false,"stayTime":0.0,"acceleration":0.0},"playerWallData_Left":{"playWallCount":-1,"isCanPlayWall":false,"stayTime":0.0,"acceleration":0.0},"localPosition":"52,-2,0","localRotation":"0,0,0","localScale":"16,8,6.824931","left_x":44,"parentName":"collider","luaName":"FlatSurface","param":""},{"items":[{"localPosition":"-1.636,0,0","localRotation":"0,0,0","localScale":"-0.75,0.75,0.75","material_id":"15020000"},{"localPosition":"-0.815,0,0","localRotation":"0,0,0","localScale":"-0.75,0.75,0.75","material_id":"15020000"},{"localPosition":"0,0,0","localRotation":"0,0,0","localScale":"-0.75,0.75,0.75","material_id":"15020000"},{"localPosition":"0.829,0,0","localRotation":"0,0,0","localScale":"-0.75,0.75,0.75","material_id":"15020000"},{"localPosition":"1.643,0,0","localRotation":"0,0,0","localScale":"-0.75,0.75,0.75","material_id":"15020000"}],"localPosition":"46.37,3.28,0","localRotation":"0,0,0","localScale":"1,1,1","left_x":44,"parentName":"item","luaName":"EliminateItemGroup","param":""},{"localPosition":"44.81,2.58,0","localRotation":"0,0,0","localScale":"1,1,1","left_x":44,"parentName":"bouncing","luaName":"RevivePointMark","param":""},{"localPosition":"46.5,2.68,0","localRotation":"0,0,0","localScale":"1,1,1","left_x":46,"parentName":"bouncing","luaName":"HolyLandingPointMark","param":""},{"localPosition":"48.97,6,0","localRotation":"0,0,0","localScale":"1,1,1","left_x":48,"parentName":"bouncing","luaName":"RhubarbDuckPointMark","param":""},{"collider_center":null,"collider_radius":null,"collider_height":null,"localPosition":"51.55,2,0","localRotation":"0,0,0","localScale":"1.5,1.5,-1.5","left_x":50,"parentName":"monster","luaName":"SlideMoleEnemy","param":"15106000"},{"trigger_localPosition":"-1.29,1.49,0","trigger_localRotation":"0,0,0","trigger_localScale":"1,1,1","trigger_size":"1,8,3","objects":[{"luaName":"MovingSurface","localPosition":"0.5999908,-10,0","localRotation":"0,0,0","localScale":"4,1,7","childLocalScale":"0.1428571,1,0.25","material_id":"scenes_common_cloudroad01c","path":[{"speed":40.0,"delay":0.0,"loopType":"none","easeType":"easeInOutSine","rotateAngle":"0,0,0","nodes":["0,1,0","0,7,0"]}]},{"luaName":"MovingSurface","localPosition":"20.6,-10,0","localRotation":"0,0,0","localScale":"4,1,7","childLocalScale":"0.1428571,1,0.25","material_id":"scenes_common_cloudroad01c","path":[{"speed":40.0,"delay":1.5,"loopType":"none","easeType":"easeInOutSine","rotateAngle":"0,0,0","nodes":["0,0,0","0,7,0"]}]},{"luaName":"MovingSurface","localPosition":"4.599998,-10,0","localRotation":"0,0,0","localScale":"4,1,7","childLocalScale":"0.1428571,1,0.25","material_id":"scenes_common_cloudroad01c","path":[{"speed":40.0,"delay":0.2,"loopType":"none","easeType":"easeInOutSine","rotateAngle":"0,0,0","nodes":["0,0,0","0,7,0"]}]},{"luaName":"MovingSurface","localPosition":"8.599998,-10,0","localRotation":"0,0,0","localScale":"4,1,7","childLocalScale":"0.1428571,1,0.25","material_id":"scenes_common_cloudroad01c","path":[{"speed":40.0,"delay":0.5,"loopType":"none","easeType":"easeInOutSine","rotateAngle":"0,0,0","nodes":["0,0,0","0,7,0"]}]},{"luaName":"MovingSurface","localPosition":"12.6,-10,0","localRotation":"0,0,0","localScale":"4,1,7","childLocalScale":"0.1428571,1,0.25","material_id":"scenes_common_cloudroad01c","path":[{"speed":40.0,"delay":0.9,"loopType":"none","easeType":"easeInOutSine","rotateAngle":"0,0,0","nodes":["0,0,0","0,7,0"]}]},{"luaName":"MovingSurface","localPosition":"16.6,-10,0","localRotation":"0,0,0","localScale":"4,1,7","childLocalScale":"0.1428571,1,0.25","material_id":"scenes_common_cloudroad01c","path":[{"speed":40.0,"delay":1.2,"loopType":"none","easeType":"easeInOutSine","rotateAngle":"0,0,0","nodes":["0,0,0","0,7,0"]}]}],"localPosition":"61.39,4.5,0","localRotation":"0,0,0","localScale":"1,1,1","left_x":59,"parentName":"monster","luaName":"AnimTriggerItem","param":""},{"items":[{"localPosition":"-0.81,0.54,0","localRotation":"0,0,0","localScale":"-0.75,0.75,0.75","material_id":"15020000"},{"localPosition":"0,0.54,0","localRotation":"0,0,0","localScale":"-0.75,0.75,0.75","material_id":"15020000"},{"localPosition":"0.83,0.54,0","localRotation":"0,0,0","localScale":"-0.75,0.75,0.75","material_id":"15020000"},{"localPosition":"1.64,0.54,0","localRotation":"0,0,0","localScale":"-0.75,0.75,0.75","material_id":"15020000"},{"localPosition":"-1.64,0.54,0","localRotation":"0,0,0","localScale":"-0.75,0.75,0.75","material_id":"15020000"},{"localPosition":"1.64,-0.12,0","localRotation":"0,0,0","localScale":"-0.75,0.75,0.75","material_id":"15020000"},{"localPosition":"0.83,-0.12,0","localRotation":"0,0,0","localScale":"-0.75,0.75,0.75","material_id":"15020000"},{"localPosition":"0,-0.12,0","localRotation":"0,0,0","localScale":"-0.75,0.75,0.75","material_id":"15020000"},{"localPosition":"-0.81,-0.12,0","localRotation":"0,0,0","localScale":"-0.75,0.75,0.75","material_id":"15020000"},{"localPosition":"-1.64,-0.12,0","localRotation":"0,0,0","localScale":"-0.75,0.75,0.75","material_id":"15020000"},{"localPosition":"0.84,1.19,0","localRotation":"0,0,0","localScale":"-0.75,0.75,0.75","material_id":"15020000"},{"localPosition":"0.84,-0.77,0","localRotation":"0,0,0","localScale":"-0.75,0.75,0.75","material_id":"15020000"},{"localPosition":"2.41,0.25,0","localRotation":"0,0,0","localScale":"-0.75,0.75,0.75","material_id":"15020000"}],"localPosition":"62.59,3.51,0","localRotation":"0,0,0","localScale":"1,1,1","left_x":60,"parentName":"item","luaName":"EliminateItemGroup","param":""},{"items":[{"localPosition":"-0.81,0.54,0","localRotation":"0,0,0","localScale":"-0.75,0.75,0.75","material_id":"15020000"},{"localPosition":"0,0.54,0","localRotation":"0,0,0","localScale":"-0.75,0.75,0.75","material_id":"15020000"},{"localPosition":"0.83,0.54,0","localRotation":"0,0,0","localScale":"-0.75,0.75,0.75","material_id":"15020000"},{"localPosition":"1.64,0.54,0","localRotation":"0,0,0","localScale":"-0.75,0.75,0.75","material_id":"15020000"},{"localPosition":"-1.64,0.54,0","localRotation":"0,0,0","localScale":"-0.75,0.75,0.75","material_id":"15020000"},{"localPosition":"1.64,-0.12,0","localRotation":"0,0,0","localScale":"-0.75,0.75,0.75","material_id":"15020000"},{"localPosition":"0.83,-0.12,0","localRotation":"0,0,0","localScale":"-0.75,0.75,0.75","material_id":"15020000"},{"localPosition":"0,-0.12,0","localRotation":"0,0,0","localScale":"-0.75,0.75,0.75","material_id":"15020000"},{"localPosition":"-0.81,-0.12,0","localRotation":"0,0,0","localScale":"-0.75,0.75,0.75","material_id":"15020000"},{"localPosition":"-1.64,-0.12,0","localRotation":"0,0,0","localScale":"-0.75,0.75,0.75","material_id":"15020000"},{"localPosition":"0.84,1.19,0","localRotation":"0,0,0","localScale":"-0.75,0.75,0.75","material_id":"15020000"},{"localPosition":"0.84,-0.77,0","localRotation":"0,0,0","localScale":"-0.75,0.75,0.75","material_id":"15020000"},{"localPosition":"2.41,0.25,0","localRotation":"0,0,0","localScale":"-0.75,0.75,0.75","material_id":"15020000"}],"localPosition":"69.62,3.56,0","localRotation":"0,0,0","localScale":"1,1,1","left_x":67,"parentName":"item","luaName":"EliminateItemGroup","param":""},{"items":[{"localPosition":"-0.81,0.54,0","localRotation":"0,0,0","localScale":"-0.75,0.75,0.75","material_id":"15020000"},{"localPosition":"0,0.54,0","localRotation":"0,0,0","localScale":"-0.75,0.75,0.75","material_id":"15020000"},{"localPosition":"0.83,0.54,0","localRotation":"0,0,0","localScale":"-0.75,0.75,0.75","material_id":"15020000"},{"localPosition":"1.64,0.54,0","localRotation":"0,0,0","localScale":"-0.75,0.75,0.75","material_id":"15020000"},{"localPosition":"-1.64,0.54,0","localRotation":"0,0,0","localScale":"-0.75,0.75,0.75","material_id":"15020000"},{"localPosition":"1.64,-0.12,0","localRotation":"0,0,0","localScale":"-0.75,0.75,0.75","material_id":"15020000"},{"localPosition":"0.83,-0.12,0","localRotation":"0,0,0","localScale":"-0.75,0.75,0.75","material_id":"15020000"},{"localPosition":"0,-0.12,0","localRotation":"0,0,0","localScale":"-0.75,0.75,0.75","material_id":"15020000"},{"localPosition":"-0.81,-0.12,0","localRotation":"0,0,0","localScale":"-0.75,0.75,0.75","material_id":"15020000"},{"localPosition":"-1.64,-0.12,0","localRotation":"0,0,0","localScale":"-0.75,0.75,0.75","material_id":"15020000"},{"localPosition":"0.84,1.19,0","localRotation":"0,0,0","localScale":"-0.75,0.75,0.75","material_id":"15020000"},{"localPosition":"0.84,-0.77,0","localRotation":"0,0,0","localScale":"-0.75,0.75,0.75","material_id":"15020000"},{"localPosition":"2.41,0.25,0","localRotation":"0,0,0","localScale":"-0.75,0.75,0.75","material_id":"15020000"}],"localPosition":"76.69,3.56,0","localRotation":"0,0,0","localScale":"1,1,1","left_x":74,"parentName":"item","luaName":"EliminateItemGroup","param":""},{"trigger_localPosition":"-15.99,2.98,0","trigger_localRotation":"0,0,0","trigger_localScale":"1,1,1","trigger_size":"1,8,3","objects":[{"luaName":"FlightEnemy","localPosition":"-5.760002,-0.5700002,0","localRotation":"0,0,0","localScale":"1.5,1.5,-1.5","childLocalScale":"1,1,1","material_id":"15031000","path":[{"speed":12.0,"delay":0.0,"loopType":"none","easeType":"linear","rotateAngle":"0,0,0","nodes":["0,0,0","-12,0,0"]}]},{"luaName":"FlightEnemy","localPosition":"-4.760002,0.9299998,0","localRotation":"0,0,0","localScale":"1.5,1.5,-1.5","childLocalScale":"1,1,1","material_id":"15031000","path":[{"speed":12.0,"delay":0.0,"loopType":"none","easeType":"linear","rotateAngle":"0,0,0","nodes":["0,0,0","-12,0,0"]}]}],"localPosition":"95.95,2.92,0","localRotation":"0,0,0","localScale":"1,1,1","left_x":79,"parentName":"monster","luaName":"AnimTriggerItem","param":""},{"playerWallData_Right":{"playWallCount":-1,"isCanPlayWall":false,"stayTime":0.0,"acceleration":0.0},"playerWallData_Left":{"playWallCount":-1,"isCanPlayWall":false,"stayTime":0.0,"acceleration":0.0},"localPosition":"90,-3,0","localRotation":"0,0,0","localScale":"8.5,6,6.824931","left_x":85,"parentName":"collider","luaName":"FlatSurface","param":""},{"localPosition":"87.22,0.92,0","localRotation":"0,0,0","localScale":"1,1,1","left_x":86,"parentName":"bouncing","luaName":"RhubarbDuckPointMark","param":""},{"localPosition":"87.96,0.62,0","localRotation":"0,0,0","localScale":"1,1,1","left_x":87,"parentName":"bouncing","luaName":"RevivePointMark","param":""},{"items":[{"localPosition":"-3.779,2.318,0","localRotation":"0,0,0","localScale":"-0.75,0.75,0.75","material_id":"15020000"},{"localPosition":"-6.426,-1.036,0","localRotation":"0,0,0","localScale":"-0.75,0.75,0.75","material_id":"15020000"},{"localPosition":"-6.27,-0.39,0","localRotation":"0,0,0","localScale":"-0.75,0.75,0.75","material_id":"15020000"},{"localPosition":"-1.3,-0.39,0","localRotation":"0,0,0","localScale":"-0.75,0.75,0.75","material_id":"15020000"},{"localPosition":"-6.01,0.25,0","localRotation":"0,0,0","localScale":"-0.75,0.75,0.75","material_id":"15020000"},{"localPosition":"-1.57,0.25,0","localRotation":"0,0,0","localScale":"-0.75,0.75,0.75","material_id":"15020000"},{"localPosition":"-5.63,0.89,0","localRotation":"0,0,0","localScale":"-0.75,0.75,0.75","material_id":"15020000"},{"localPosition":"-1.93,0.89,0","localRotation":"0,0,0","localScale":"-0.75,0.75,0.75","material_id":"15020000"},{"localPosition":"-5.16,1.54,0","localRotation":"0,0,0","localScale":"-0.75,0.75,0.75","material_id":"15020000"},{"localPosition":"-2.42,1.54,0","localRotation":"0,0,0","localScale":"-0.75,0.75,0.75","material_id":"15020000"},{"localPosition":"-4.5,2.02,0","localRotation":"0,0,0","localScale":"-0.75,0.75,0.75","material_id":"15020000"},{"localPosition":"-3.07,2.02,0","localRotation":"0,0,0","localScale":"-0.75,0.75,0.75","material_id":"15020000"}],"localPosition":"100.363,2,0","localRotation":"0,0,0","localScale":"1,1,1","left_x":93,"parentName":"item","luaName":"EliminateItemGroup","param":""},{"step_localPosition":"0,0.79,0","step_localScale":"3,0.4,6","bouncing_model_name":"jelly_yellow","bouncing_model_localPosition":"0,0,0","bouncing_model_localRotation":"2.504478E-06,0,0","bouncing_model_localScale":"1,1,1","target_localPosition":"","bouncing_path":[{"speed":15.0,"delay":0.0,"loopType":"none","easeType":"easeOutExpo","rotateAngle":"0,0,0","nodes":["0.7656021,0.8981186,0","4.421936,1.372359,0"]}],"localPosition":"99.46,-0.58,0","localRotation":"0,0,0","localScale":"1,1,1","left_x":97,"parentName":"bouncing","luaName":"BouncingSurface","param":"60;3;0;0;1","m_TargetZ":0.0,"m_isReplaceAction":1.0,"m_Direction":1.0,"m_ActionSpeed":1.0,"m_ActionDelayTime":0.0},{"localPosition":"97.81,1.69,0","localRotation":"0,0,0","localScale":"1,1,1","left_x":97,"parentName":"bouncing","luaName":"CameraZMoveItem","param":"2;0,6,-5"},{"step_localPosition":"0,0.78,0","step_localScale":"3,0.4,6","bouncing_model_name":"jelly_yellow","bouncing_model_localPosition":"0,0,0","bouncing_model_localRotation":"2.504478E-06,0,0","bouncing_model_localScale":"1,1,1","target_localPosition":"","bouncing_path":[{"speed":15.0,"delay":0.0,"loopType":"none","easeType":"easeOutExpo","rotateAngle":"0,0,0","nodes":["0.833313,0.9123954,0","4.452515,1.344307,0"]}],"localPosition":"101.95,-0.16,0","localRotation":"0,0,0","localScale":"1,1,1","left_x":100,"parentName":"bouncing","luaName":"BouncingSurface","param":"60;3;0;0;1","m_TargetZ":0.0,"m_isReplaceAction":1.0,"m_Direction":1.0,"m_ActionSpeed":1.0,"m_ActionDelayTime":0.0},{"step_localPosition":"0,0.79,0","step_localScale":"3,0.4,6","bouncing_model_name":"jelly_yellow","bouncing_model_localPosition":"0,0,0","bouncing_model_localRotation":"2.504478E-06,0,0","bouncing_model_localScale":"1,1,1","target_localPosition":"","bouncing_path":[{"speed":20.0,"delay":0.0,"loopType":"none","easeType":"easeOutQuint","rotateAngle":"0,0,0","nodes":["0.425705,1.223901,0","6.382576,8.025428,0","9.796577,9.169113,0","12.93076,6.944307,0"]}],"localPosition":"104.4,0.25,0","localRotation":"0,0,0","localScale":"1,1,1","left_x":102,"parentName":"bouncing","luaName":"BouncingSurface","param":"60;3;0","m_TargetZ":0.0,"m_isReplaceAction":1.0,"m_Direction":1.0,"m_ActionSpeed":1.0,"m_ActionDelayTime":0.0},{"step_localPosition":"0,0.4,0","step_localScale":"2,0.4,6","bouncing_model_name":"jelly_yellow","bouncing_model_localPosition":"0,0,0","bouncing_model_localRotation":"2.504478E-06,0,0","bouncing_model_localScale":"1,1,1","target_localPosition":"","bouncing_path":[{"speed":20.0,"delay":0.0,"loopType":"none","easeType":"easeOutExpo","rotateAngle":"0,0,0","nodes":["0,0.7421083,0","1.483208,3.534372,0","3.605629,0.5249,0"]}],"localPosition":"117.01,7.22,0","localRotation":"0,0,0","localScale":"1,1,1","left_x":115,"parentName":"bouncing","luaName":"BouncingSurface","param":"60;3;0","m_TargetZ":0.0,"m_isReplaceAction":1.0,"m_Direction":1.0,"m_ActionSpeed":1.0,"m_ActionDelayTime":0.0},{"step_localPosition":"0,0.4,0","step_localScale":"2,0.4,6","bouncing_model_name":"jelly_yellow","bouncing_model_localPosition":"0,0,0","bouncing_model_localRotation":"350,0,0","bouncing_model_localScale":"1,1,1","target_localPosition":"","bouncing_path":[{"speed":40.0,"delay":0.0,"loopType":"none","easeType":"linear","rotateAngle":"0,0,0","nodes":["0.1434326,0.7533326,0","3.088264,4.030728,5","6.621445,2.928601,10"]}],"localPosition":"118.2,4.03,0","localRotation":"0,0,0","localScale":"1,1,1","left_x":116,"parentName":"bouncing","luaName":"BouncingSurface","param":"60;3;0","m_TargetZ":0.0,"m_isReplaceAction":1.0,"m_Direction":1.0,"m_ActionSpeed":1.0,"m_ActionDelayTime":0.0},{"step_localPosition":"0,0.4,0","step_localScale":"2,0.4,6","bouncing_model_name":"jelly_yellow","bouncing_model_localPosition":"0,0,0","bouncing_model_localRotation":"355,0,0","bouncing_model_localScale":"1,1,1","target_localPosition":"","bouncing_path":[{"speed":20.0,"delay":0.0,"loopType":"none","easeType":"easeOutExpo","rotateAngle":"0,0,0","nodes":["0.0923996,0.7392254,0","2.510284,2.510288,0","3.927139,0.4928169,0"]}],"localPosition":"118.52,10.26,0","localRotation":"0,0,0","localScale":"1,1,1","left_x":116,"parentName":"bouncing","luaName":"BouncingSurface","param":"","m_TargetZ":0.0,"m_isReplaceAction":1.0,"m_Direction":1.0,"m_ActionSpeed":1.0,"m_ActionDelayTime":0.0},{"step_localPosition":"0,0.4,0","step_localScale":"2,0.4,6","bouncing_model_name":"jelly_yellow","bouncing_model_localPosition":"0,0,0","bouncing_model_localRotation":"340,0,0","bouncing_model_localScale":"1,1,1","target_localPosition":"","bouncing_path":[{"speed":20.0,"delay":0.0,"loopType":"none","easeType":"easeOutExpo","rotateAngle":"0,0,0","nodes":["-0.2744293,0.7622988,0","-2.327553,2.967883,0","-0.02033234,3.618378,0"]}],"localPosition":"120.95,1.54,0","localRotation":"0,0,0","localScale":"1,1,1","left_x":119,"parentName":"bouncing","luaName":"BouncingSurface","param":"","m_TargetZ":0.0,"m_isReplaceAction":1.0,"m_Direction":1.0,"m_ActionSpeed":1.0,"m_ActionDelayTime":0.0},{"step_localPosition":"0,0.4,0","step_localScale":"2,0.4,6","bouncing_model_name":"jelly_yellow","bouncing_model_localPosition":"0,0,0","bouncing_model_localRotation":"350,0,0","bouncing_model_localScale":"1,1,1","target_localPosition":"","bouncing_path":[{"speed":20.0,"delay":0.0,"loopType":"none","easeType":"easeOutExpo","rotateAngle":"0,0,0","nodes":["0.1749268,0.728838,0","3.29435,1.525701,0","3.758392,-1.643205,0"]}],"localPosition":"120.99,12.37,0","localRotation":"0,0,0","localScale":"1,1,1","left_x":119,"parentName":"bouncing","luaName":"BouncingSurface","param":"","m_TargetZ":0.0,"m_isReplaceAction":1.0,"m_Direction":1.0,"m_ActionSpeed":1.0,"m_ActionDelayTime":0.0},{"step_localPosition":"0,0.4,0","step_localScale":"2,0.4,6","bouncing_model_name":"jelly_yellow","bouncing_model_localPosition":"0,0,0","bouncing_model_localRotation":"345,0,0","bouncing_model_localScale":"1,1,1","target_localPosition":"","bouncing_path":[{"speed":20.0,"delay":0.0,"loopType":"none","easeType":"easeOutExpo","rotateAngle":"0,0,0","nodes":["0.6902847,0.6781712,0","3.475624,-0.8477135,0","0.9324799,-2.676353,0"]}],"localPosition":"124.26,13.51,0","localRotation":"0,0,0","localScale":"1,1,1","left_x":122,"parentName":"bouncing","luaName":"BouncingSurface","param":"","m_TargetZ":0.0,"m_isReplaceAction":1.0,"m_Direction":1.0,"m_ActionSpeed":1.0,"m_ActionDelayTime":0.0},{"step_localPosition":"0,0.4,0","step_localScale":"2,0.4,6","bouncing_model_name":"jelly_yellow","bouncing_model_localPosition":"0,0,0","bouncing_model_localRotation":"320,0,0","bouncing_model_localScale":"1,1,1","target_localPosition":"24.36,-5.18,-10","bouncing_path":null,"localPosition":"124.82,6.46,10","localRotation":"0,0,0","localScale":"1,1,1","left_x":123,"parentName":"bouncing","luaName":"BouncingSurface","param":"60;3;0","m_TargetZ":0.0,"m_isReplaceAction":1.0,"m_Direction":1.0,"m_ActionSpeed":1.0,"m_ActionDelayTime":0.0},{"step_localPosition":"0,0.4,0","step_localScale":"2,0.4,6","bouncing_model_name":"jelly_yellow","bouncing_model_localPosition":"0,0,0","bouncing_model_localRotation":"330,0,0","bouncing_model_localScale":"1,1,1","target_localPosition":"","bouncing_path":[{"speed":20.0,"delay":0.0,"loopType":"none","easeType":"easeOutExpo","rotateAngle":"0,0,0","nodes":["-0.2684021,0.7235117,0","-3.556625,1.585687,0","-1.984314,3.403503,0"]}],"localPosition":"125,0.39,0","localRotation":"0,0,0","localScale":"1,1,1","left_x":123,"parentName":"bouncing","luaName":"BouncingSurface","param":"","m_TargetZ":0.0,"m_isReplaceAction":1.0,"m_Direction":1.0,"m_ActionSpeed":1.0,"m_ActionDelayTime":0.0},{"localPosition":"124.19,7.63,10","localRotation":"0,0,0","localScale":"1,1,1","left_x":123,"parentName":"bouncing","luaName":"RevivePointMark","param":""},{"step_localPosition":"0,0.4,0","step_localScale":"2,0.4,6","bouncing_model_name":"jelly_yellow","bouncing_model_localPosition":"0,0,0","bouncing_model_localRotation":"340,0,0","bouncing_model_localScale":"1,1,1","target_localPosition":"","bouncing_path":[{"speed":20.0,"delay":0.0,"loopType":"none","easeType":"easeOutExpo","rotateAngle":"0,0,0","nodes":["0.5207367,0.1089926,0","2.519928,-1.456594,0","-0.5691757,-3.172871,0"]}],"localPosition":"127.66,12.34,0","localRotation":"0,0,0","localScale":"1,1,1","left_x":126,"parentName":"bouncing","luaName":"BouncingSurface","param":"","m_TargetZ":0.0,"m_isReplaceAction":1.0,"m_Direction":1.0,"m_ActionSpeed":1.0,"m_ActionDelayTime":0.0},{"step_localPosition":"0,0.4,0","step_localScale":"2,0.4,6","bouncing_model_name":"jelly_yellow","bouncing_model_localPosition":"0,0,0","bouncing_model_localRotation":"320,0,0","bouncing_model_localScale":"1,1,1","target_localPosition":"","bouncing_path":[{"speed":20.0,"delay":0.0,"loopType":"none","easeType":"easeOutExpo","rotateAngle":"0,0,0","nodes":["-0.4634399,0.135644,0","-3.798035,-0.9155974,0","-4.306702,1.10776,0"]}],"localPosition":"128.86,1.76,0","localRotation":"0,0,0","localScale":"1,1,1","left_x":127,"parentName":"bouncing","luaName":"BouncingSurface","param":"","m_TargetZ":0.0,"m_isReplaceAction":1.0,"m_Direction":1.0,"m_ActionSpeed":1.0,"m_ActionDelayTime":0.0},{"step_localPosition":"0,0.4,0","step_localScale":"2,0.4,6","bouncing_model_name":"jelly_yellow","bouncing_model_localPosition":"0,0,0","bouncing_model_localRotation":"335,0,0","bouncing_model_localScale":"1,1,1","target_localPosition":"","bouncing_path":[{"speed":20.0,"delay":0.0,"loopType":"none","easeType":"easeOutExpo","rotateAngle":"0,0,0","nodes":["0.2472076,0.1318417,0","1.582123,-2.636847,0","-1.812836,-1.730432,0"]}],"localPosition":"130.24,10.48,0","localRotation":"0,0,0","localScale":"1,1,1","left_x":128,"parentName":"bouncing","luaName":"BouncingSurface","param":"","m_TargetZ":0.0,"m_isReplaceAction":1.0,"m_Direction":1.0,"m_ActionSpeed":1.0,"m_ActionDelayTime":0.0},{"step_localPosition":"0,0.4,0","step_localScale":"2,0.4,6","bouncing_model_name":"jelly_yellow","bouncing_model_localPosition":"0,0,0","bouncing_model_localRotation":"325,0,0","bouncing_model_localScale":"1,1,1","target_localPosition":"","bouncing_path":[{"speed":20.0,"delay":0.0,"loopType":"none","easeType":"easeOutExpo","rotateAngle":"0,0,0","nodes":["0,0,0","-2.174133,-2.12473,0","-3.804741,0.03294182,0"]}],"localPosition":"131.08,4.26,0","localRotation":"0,0,0","localScale":"1,1,1","left_x":129,"parentName":"bouncing","luaName":"BouncingSurface","param":"","m_TargetZ":0.0,"m_isReplaceAction":1.0,"m_Direction":1.0,"m_ActionSpeed":1.0,"m_ActionDelayTime":0.0},{"step_localPosition":"0,0.4,0","step_localScale":"2,0.4,6","bouncing_model_name":"jelly_yellow","bouncing_model_localPosition":"0,0,0","bouncing_model_localRotation":"330,0,0","bouncing_model_localScale":"1,1,1","target_localPosition":"","bouncing_path":[{"speed":20.0,"delay":0.0,"loopType":"none","easeType":"easeOutExpo","rotateAngle":"0,0,0","nodes":["0,0,0","-0.7287903,-2.776333,0","-3.284073,-0.841013,0"]}],"localPosition":"131.76,7.4,0","localRotation":"0,0,0","localScale":"1,1,1","left_x":130,"parentName":"bouncing","luaName":"BouncingSurface","param":"","m_TargetZ":0.0,"m_isReplaceAction":1.0,"m_Direction":1.0,"m_ActionSpeed":1.0,"m_ActionDelayTime":0.0},{"playerWallData_Right":{"playWallCount":-1,"isCanPlayWall":false,"stayTime":0.0,"acceleration":0.0},"playerWallData_Left":{"playWallCount":-1,"isCanPlayWall":false,"stayTime":0.0,"acceleration":0.0},"localPosition":"155,-3,0","localRotation":"0,0,0","localScale":"16,6,7","left_x":147,"parentName":"collider","luaName":"FlatSurface","param":""},{"localPosition":"148.27,1.41,0","localRotation":"0,0,0","localScale":"1,1,1","left_x":147,"parentName":"bouncing","luaName":"RhubarbDuckPointMark","param":""},{"localPosition":"148.2,0.9,0","localRotation":"0,0,0","localScale":"1,1,1","left_x":147,"parentName":"bouncing","luaName":"RevivePointMark","param":""},{"localPosition":"147.52,0.54,0","localRotation":"0,0,0","localScale":"1,1,1","left_x":147,"parentName":"bouncing","luaName":"CameraZMoveItem","param":"1"},{"localPosition":"149.8,0.64,0","localRotation":"0,0,0","localScale":"1,1,1","left_x":149,"parentName":"bouncing","luaName":"HolyLandingPointMark","param":""},{"collider_center":null,"collider_radius":null,"collider_height":null,"localPosition":"154.15,0,0","localRotation":"0,0,0","localScale":"1.5,1.5,-1.5","left_x":153,"parentName":"monster","luaName":"SlideMoleEnemy","param":"15106000"},{"collider_center":null,"collider_radius":null,"collider_height":null,"localPosition":"157.95,0,0","localRotation":"0,0,0","localScale":"1.5,1.5,-1.5","left_x":157,"parentName":"monster","luaName":"SlideMoleEnemy","param":"15106000"},{"trigger_localPosition":"-5.05,3,0","trigger_localRotation":"0,0,0","trigger_localScale":"1,1,1","trigger_size":"1,8,3","objects":[{"luaName":"KoffingEnemy","localPosition":"0,0,0","localRotation":"0,90.00001,0","localScale":"1.2,1.2,-1.2","childLocalScale":"1,1,1","material_id":"15030000","path":[{"speed":30.0,"delay":0.0,"loopType":"none","easeType":"easeInOutSine","rotateAngle":"0,0,0","nodes":["0,0,0","0,-4,0","0,0,0"]}]}],"localPosition":"164.5,1,0","localRotation":"0,0,0","localScale":"1,1,1","left_x":158,"parentName":"monster","luaName":"AnimTriggerItem","param":""},{"items":[{"localPosition":"-3.779,2.318,0","localRotation":"0,0,0","localScale":"-0.75,0.75,0.75","material_id":"15020000"},{"localPosition":"-6.426,-1.036,0","localRotation":"0,0,0","localScale":"-0.75,0.75,0.75","material_id":"15020000"},{"localPosition":"-6.27,-0.39,0","localRotation":"0,0,0","localScale":"-0.75,0.75,0.75","material_id":"15020000"},{"localPosition":"-6.01,0.25,0","localRotation":"0,0,0","localScale":"-0.75,0.75,0.75","material_id":"15020000"},{"localPosition":"-5.63,0.89,0","localRotation":"0,0,0","localScale":"-0.75,0.75,0.75","material_id":"15020000"},{"localPosition":"-1.93,0.89,0","localRotation":"0,0,0","localScale":"-0.75,0.75,0.75","material_id":"15020000"},{"localPosition":"-5.16,1.54,0","localRotation":"0,0,0","localScale":"-0.75,0.75,0.75","material_id":"15020000"},{"localPosition":"-2.42,1.54,0","localRotation":"0,0,0","localScale":"-0.75,0.75,0.75","material_id":"15020000"},{"localPosition":"-4.5,2.02,0","localRotation":"0,0,0","localScale":"-0.75,0.75,0.75","material_id":"15020000"},{"localPosition":"-3.07,2.02,0","localRotation":"0,0,0","localScale":"-0.75,0.75,0.75","material_id":"15020000"}],"localPosition":"168.56,2.31,0","localRotation":"0,0,0","localScale":"1,1,1","left_x":161,"parentName":"item","luaName":"EliminateItemGroup","param":""},{"playerWallData_Right":{"playWallCount":-1,"isCanPlayWall":false,"stayTime":0.0,"acceleration":0.0},"playerWallData_Left":{"playWallCount":-1,"isCanPlayWall":false,"stayTime":0.0,"acceleration":0.0},"localPosition":"169,-2,0","localRotation":"0,0,0","localScale":"6,8,6.824931","left_x":166,"parentName":"collider","luaName":"FlatSurface","param":""},{"items":[{"localPosition":"-1.636,0,0","localRotation":"0,0,0","localScale":"-0.75,0.75,0.75","material_id":"15020000"},{"localPosition":"-0.815,0,0","localRotation":"0,0,0","localScale":"-0.75,0.75,0.75","material_id":"15020000"},{"localPosition":"0,0,0","localRotation":"0,0,0","localScale":"-0.75,0.75,0.75","material_id":"15020000"},{"localPosition":"0.829,0,0","localRotation":"0,0,0","localScale":"-0.75,0.75,0.75","material_id":"15020000"},{"localPosition":"1.643,0,0","localRotation":"0,0,0","localScale":"-0.75,0.75,0.75","material_id":"15020000"}],"localPosition":"169.078,3.196036,0","localRotation":"0,0,0","localScale":"1,1,1","left_x":166,"parentName":"item","luaName":"EliminateItemGroup","param":""},{"localPosition":"166.9,2.59,0","localRotation":"0,0,0","localScale":"1,1,1","left_x":166,"parentName":"bouncing","luaName":"RevivePointMark","param":""},{"trigger_localPosition":"-5.05,3,0","trigger_localRotation":"0,0,0","trigger_localScale":"1,1,1","trigger_size":"1,8,3","objects":[{"luaName":"KoffingEnemy","localPosition":"0,0,0","localRotation":"0,90.00001,0","localScale":"1.2,1.2,-1.2","childLocalScale":"1,1,1","material_id":"15030000","path":[{"speed":30.0,"delay":0.0,"loopType":"none","easeType":"easeInOutSine","rotateAngle":"0,0,0","nodes":["0,0,0","0,-4,0","0,0,0"]}]}],"localPosition":"173.5,3,0","localRotation":"0,0,0","localScale":"1,1,1","left_x":167,"parentName":"monster","luaName":"AnimTriggerItem","param":""},{"items":[{"localPosition":"-3.779,2.318,0","localRotation":"0,0,0","localScale":"-0.75,0.75,0.75","material_id":"15020000"},{"localPosition":"-6.426,-1.036,0","localRotation":"0,0,0","localScale":"-0.75,0.75,0.75","material_id":"15020000"},{"localPosition":"-6.27,-0.39,0","localRotation":"0,0,0","localScale":"-0.75,0.75,0.75","material_id":"15020000"},{"localPosition":"-6.01,0.25,0","localRotation":"0,0,0","localScale":"-0.75,0.75,0.75","material_id":"15020000"},{"localPosition":"-5.63,0.89,0","localRotation":"0,0,0","localScale":"-0.75,0.75,0.75","material_id":"15020000"},{"localPosition":"-1.93,0.89,0","localRotation":"0,0,0","localScale":"-0.75,0.75,0.75","material_id":"15020000"},{"localPosition":"-5.16,1.54,0","localRotation":"0,0,0","localScale":"-0.75,0.75,0.75","material_id":"15020000"},{"localPosition":"-2.42,1.54,0","localRotation":"0,0,0","localScale":"-0.75,0.75,0.75","material_id":"15020000"},{"localPosition":"-4.5,2.02,0","localRotation":"0,0,0","localScale":"-0.75,0.75,0.75","material_id":"15020000"},{"localPosition":"-3.07,2.02,0","localRotation":"0,0,0","localScale":"-0.75,0.75,0.75","material_id":"15020000"}],"localPosition":"177.92,4.26,0","localRotation":"0,0,0","localScale":"1,1,1","left_x":171,"parentName":"item","luaName":"EliminateItemGroup","param":""},{"playerWallData_Right":{"playWallCount":-1,"isCanPlayWall":false,"stayTime":0.0,"acceleration":0.0},"playerWallData_Left":{"playWallCount":-1,"isCanPlayWall":false,"stayTime":0.0,"acceleration":0.0},"localPosition":"179,-1,0","localRotation":"0,0,0","localScale":"8,10,6.824931","left_x":175,"parentName":"collider","luaName":"FlatSurface","param":""},{"localPosition":"175.99,4.59,0","localRotation":"0,0,0","localScale":"1,1,1","left_x":175,"parentName":"bouncing","luaName":"RevivePointMark","param":""},{"localPosition":"177.15,6.29,0","localRotation":"0,0,0","localScale":"1,1,1","left_x":176,"parentName":"bouncing","luaName":"RhubarbDuckPointMark","param":""},{"collider_center":null,"collider_radius":null,"collider_height":null,"localPosition":"180.33,4,0","localRotation":"0,0,0","localScale":"1.5,1.5,-1.5","left_x":179,"parentName":"monster","luaName":"SlideMoleEnemy","param":"15106000"},{"playerWallData_Right":{"playWallCount":-1,"isCanPlayWall":false,"stayTime":0.0,"acceleration":0.0},"playerWallData_Left":{"playWallCount":-1,"isCanPlayWall":false,"stayTime":0.0,"acceleration":0.0},"localPosition":"209,-1,0","localRotation":"0,0,0","localScale":"52,6,7","left_x":183,"parentName":"collider","luaName":"FlatSurface","param":""},{"localPosition":"185.73,2.74,0","localRotation":"0,0,0","localScale":"1,1,1","left_x":185,"parentName":"bouncing","luaName":"HolyLandingPointMark","param":""},{"localPosition":"192.01,4.9,0","localRotation":"0,0,0","localScale":"4,0.2,7","left_x":190,"parentName":"collider","luaName":"MonoSurface","param":""},{"items":[{"localPosition":"-3.779,2.318,0","localRotation":"0,0,0","localScale":"-0.75,0.75,0.75","material_id":"15020000"},{"localPosition":"-6.426,-1.036,0","localRotation":"0,0,0","localScale":"-0.75,0.75,0.75","material_id":"15020000"},{"localPosition":"-6.27,-0.39,0","localRotation":"0,0,0","localScale":"-0.75,0.75,0.75","material_id":"15020000"},{"localPosition":"-6.01,0.25,0","localRotation":"0,0,0","localScale":"-0.75,0.75,0.75","material_id":"15020000"},{"localPosition":"-5.63,0.89,0","localRotation":"0,0,0","localScale":"-0.75,0.75,0.75","material_id":"15020000"},{"localPosition":"-1.93,0.89,0","localRotation":"0,0,0","localScale":"-0.75,0.75,0.75","material_id":"15020000"},{"localPosition":"-5.16,1.54,0","localRotation":"0,0,0","localScale":"-0.75,0.75,0.75","material_id":"15020000"},{"localPosition":"-2.42,1.54,0","localRotation":"0,0,0","localScale":"-0.75,0.75,0.75","material_id":"15020000"},{"localPosition":"-4.5,2.02,0","localRotation":"0,0,0","localScale":"-0.75,0.75,0.75","material_id":"15020000"},{"localPosition":"-3.07,2.02,0","localRotation":"0,0,0","localScale":"-0.75,0.75,0.75","material_id":"15020000"}],"localPosition":"200,7.47,0","localRotation":"0,0,0","localScale":"1,1,1","left_x":193,"parentName":"item","luaName":"EliminateItemGroup","param":""},{"localPosition":"199.01,7.5,0","localRotation":"0,0,0","localScale":"4,0.2,7","left_x":197,"parentName":"collider","luaName":"MonoSurface","param":""},{"items":[{"localPosition":"-3.779,2.318,0","localRotation":"0,0,0","localScale":"-0.75,0.75,0.75","material_id":"15020000"},{"localPosition":"-6.426,-1.036,0","localRotation":"0,0,0","localScale":"-0.75,0.75,0.75","material_id":"15020000"},{"localPosition":"-1.154,-1.036,0","localRotation":"0,0,0","localScale":"-0.75,0.75,0.75","material_id":"15020000"},{"localPosition":"-6.27,-0.39,0","localRotation":"0,0,0","localScale":"-0.75,0.75,0.75","material_id":"15020000"},{"localPosition":"-1.3,-0.39,0","localRotation":"0,0,0","localScale":"-0.75,0.75,0.75","material_id":"15020000"},{"localPosition":"-6.01,0.25,0","localRotation":"0,0,0","localScale":"-0.75,0.75,0.75","material_id":"15020000"},{"localPosition":"-1.57,0.25,0","localRotation":"0,0,0","localScale":"-0.75,0.75,0.75","material_id":"15020000"},{"localPosition":"-5.63,0.89,0","localRotation":"0,0,0","localScale":"-0.75,0.75,0.75","material_id":"15020000"},{"localPosition":"-1.93,0.89,0","localRotation":"0,0,0","localScale":"-0.75,0.75,0.75","material_id":"15020000"},{"localPosition":"-5.16,1.54,0","localRotation":"0,0,0","localScale":"-0.75,0.75,0.75","material_id":"15020000"},{"localPosition":"-2.42,1.54,0","localRotation":"0,0,0","localScale":"-0.75,0.75,0.75","material_id":"15020000"},{"localPosition":"-4.5,2.02,0","localRotation":"0,0,0","localScale":"-0.75,0.75,0.75","material_id":"15020000"},{"localPosition":"-3.07,2.02,0","localRotation":"0,0,0","localScale":"-0.75,0.75,0.75","material_id":"15020000"}],"localPosition":"205.7175,3.864025,0","localRotation":"0,0,0","localScale":"1,1,1","left_x":198,"parentName":"item","luaName":"EliminateItemGroup","param":""},{"items":[{"localPosition":"-3.779,2.318,0","localRotation":"0,0,0","localScale":"-0.75,0.75,0.75","material_id":"15020000"},{"localPosition":"-6.426,-1.036,0","localRotation":"0,0,0","localScale":"-0.75,0.75,0.75","material_id":"15020000"},{"localPosition":"-1.154,-1.036,0","localRotation":"0,0,0","localScale":"-0.75,0.75,0.75","material_id":"15020000"},{"localPosition":"-6.27,-0.39,0","localRotation":"0,0,0","localScale":"-0.75,0.75,0.75","material_id":"15020000"},{"localPosition":"-1.3,-0.39,0","localRotation":"0,0,0","localScale":"-0.75,0.75,0.75","material_id":"15020000"},{"localPosition":"-6.01,0.25,0","localRotation":"0,0,0","localScale":"-0.75,0.75,0.75","material_id":"15020000"},{"localPosition":"-1.57,0.25,0","localRotation":"0,0,0","localScale":"-0.75,0.75,0.75","material_id":"15020000"},{"localPosition":"-5.63,0.89,0","localRotation":"0,0,0","localScale":"-0.75,0.75,0.75","material_id":"15020000"},{"localPosition":"-1.93,0.89,0","localRotation":"0,0,0","localScale":"-0.75,0.75,0.75","material_id":"15020000"},{"localPosition":"-5.16,1.54,0","localRotation":"0,0,0","localScale":"-0.75,0.75,0.75","material_id":"15020000"},{"localPosition":"-2.42,1.54,0","localRotation":"0,0,0","localScale":"-0.75,0.75,0.75","material_id":"15020000"},{"localPosition":"-4.5,2.02,0","localRotation":"0,0,0","localScale":"-0.75,0.75,0.75","material_id":"15020000"},{"localPosition":"-3.07,2.02,0","localRotation":"0,0,0","localScale":"-0.75,0.75,0.75","material_id":"15020000"}],"localPosition":"207.26,9.5,0","localRotation":"0,0,0","localScale":"1,1,1","left_x":200,"parentName":"item","luaName":"EliminateItemGroup","param":""},{"collider_center":null,"collider_radius":null,"collider_height":null,"localPosition":"202.01,3,0","localRotation":"0,90.00001,0","localScale":"1.199999,1.2,-1.199999","left_x":201,"parentName":"monster","luaName":"KoffingEnemy","param":"15030000"},{"localPosition":"206.39,2.74,0","localRotation":"0,0,0","localScale":"1,1,1","left_x":205,"parentName":"bouncing","luaName":"HolyLandingPointMark","param":""},{"localPosition":"208,7.5,0","localRotation":"0,0,0","localScale":"4,0.2,7","left_x":206,"parentName":"collider","luaName":"MonoSurface","param":""},{"items":[{"localPosition":"0.44,0.88,0","localRotation":"0,0,0","localScale":"-0.75,0.75,0.75","material_id":"15020000"},{"localPosition":"-0.39,0.88,0","localRotation":"0,0,0","localScale":"-0.75,0.75,0.75","material_id":"15020000"},{"localPosition":"-1.03,0.31,0","localRotation":"0,0,0","localScale":"-0.75,0.75,0.75","material_id":"15020000"},{"localPosition":"-1.03,-0.42,0","localRotation":"0,0,0","localScale":"-0.75,0.75,0.75","material_id":"15020000"},{"localPosition":"0,0.038,0","localRotation":"0,0,0","localScale":"1,1,1","material_id":"15021000"},{"localPosition":"1.04,-0.42,0","localRotation":"0,0,0","localScale":"-0.75,0.75,0.75","material_id":"15020000"},{"localPosition":"1.04,0.31,0","localRotation":"0,0,0","localScale":"-0.75,0.75,0.75","material_id":"15020000"},{"localPosition":"0.44,-0.852,0","localRotation":"0,0,0","localScale":"-0.75,0.75,0.75","material_id":"15020000"},{"localPosition":"-0.39,-0.852,0","localRotation":"0,0,0","localScale":"-0.75,0.75,0.75","material_id":"15020000"}],"localPosition":"207.99,8.85,0","localRotation":"0,0,0","localScale":"1,1,1","left_x":206,"parentName":"item","luaName":"EliminateItemGroup","param":""},{"items":[{"localPosition":"-3.779,2.318,0","localRotation":"0,0,0","localScale":"-0.75,0.75,0.75","material_id":"15020000"},{"localPosition":"-6.426,-1.036,0","localRotation":"0,0,0","localScale":"-0.75,0.75,0.75","material_id":"15020000"},{"localPosition":"-1.154,-1.036,0","localRotation":"0,0,0","localScale":"-0.75,0.75,0.75","material_id":"15020000"},{"localPosition":"-6.27,-0.39,0","localRotation":"0,0,0","localScale":"-0.75,0.75,0.75","material_id":"15020000"},{"localPosition":"-1.3,-0.39,0","localRotation":"0,0,0","localScale":"-0.75,0.75,0.75","material_id":"15020000"},{"localPosition":"-6.01,0.25,0","localRotation":"0,0,0","localScale":"-0.75,0.75,0.75","material_id":"15020000"},{"localPosition":"-1.57,0.25,0","localRotation":"0,0,0","localScale":"-0.75,0.75,0.75","material_id":"15020000"},{"localPosition":"-5.63,0.89,0","localRotation":"0,0,0","localScale":"-0.75,0.75,0.75","material_id":"15020000"},{"localPosition":"-1.93,0.89,0","localRotation":"0,0,0","localScale":"-0.75,0.75,0.75","material_id":"15020000"},{"localPosition":"-5.16,1.54,0","localRotation":"0,0,0","localScale":"-0.75,0.75,0.75","material_id":"15020000"},{"localPosition":"-2.42,1.54,0","localRotation":"0,0,0","localScale":"-0.75,0.75,0.75","material_id":"15020000"},{"localPosition":"-4.5,2.02,0","localRotation":"0,0,0","localScale":"-0.75,0.75,0.75","material_id":"15020000"},{"localPosition":"-3.07,2.02,0","localRotation":"0,0,0","localScale":"-0.75,0.75,0.75","material_id":"15020000"}],"localPosition":"216.27,9.5,0","localRotation":"0,0,0","localScale":"1,1,1","left_x":209,"parentName":"item","luaName":"EliminateItemGroup","param":""},{"trigger_localPosition":"-15.99,2.98,0","trigger_localRotation":"0,0,0","trigger_localScale":"1,1,1","trigger_size":"1,8,3","objects":[{"luaName":"FlightEnemy","localPosition":"-5.760002,-0.5700002,0","localRotation":"0,0,0","localScale":"1.5,1.5,-1.5","childLocalScale":"1,1,1","material_id":"15031000","path":[{"speed":12.0,"delay":0.0,"loopType":"none","easeType":"linear","rotateAngle":"0,0,0","nodes":["0,0,0","-12,0,0"]}]},{"luaName":"FlightEnemy","localPosition":"0.5,1.6,0","localRotation":"0,0,0","localScale":"1.5,1.5,-1.5","childLocalScale":"1,1,1","material_id":"15031000","path":[{"speed":12.0,"delay":0.0,"loopType":"none","easeType":"linear","rotateAngle":"0,0,0","nodes":["0,0,0","-12,0,0"]}]}],"localPosition":"225.5,2.9,0","localRotation":"0,0,0","localScale":"1,1,1","left_x":209,"parentName":"monster","luaName":"AnimTriggerItem","param":""},{"localPosition":"217,7.5,0","localRotation":"0,0,0","localScale":"4,0.2,7","left_x":215,"parentName":"collider","luaName":"MonoSurface","param":""},{"items":[{"localPosition":"0.44,0.88,0","localRotation":"0,0,0","localScale":"-0.75,0.75,0.75","material_id":"15020000"},{"localPosition":"-0.39,0.88,0","localRotation":"0,0,0","localScale":"-0.75,0.75,0.75","material_id":"15020000"},{"localPosition":"-1.03,0.31,0","localRotation":"0,0,0","localScale":"-0.75,0.75,0.75","material_id":"15020000"},{"localPosition":"-1.03,-0.42,0","localRotation":"0,0,0","localScale":"-0.75,0.75,0.75","material_id":"15020000"},{"localPosition":"0,0.038,0","localRotation":"0,0,0","localScale":"1,1,1","material_id":"15021000"},{"localPosition":"1.04,-0.42,0","localRotation":"0,0,0","localScale":"-0.75,0.75,0.75","material_id":"15020000"},{"localPosition":"1.04,0.31,0","localRotation":"0,0,0","localScale":"-0.75,0.75,0.75","material_id":"15020000"},{"localPosition":"0.44,-0.852,0","localRotation":"0,0,0","localScale":"-0.75,0.75,0.75","material_id":"15020000"},{"localPosition":"-0.39,-0.852,0","localRotation":"0,0,0","localScale":"-0.75,0.75,0.75","material_id":"15020000"}],"localPosition":"217.03,8.85,0","localRotation":"0,0,0","localScale":"1,1,1","left_x":215,"parentName":"item","luaName":"EliminateItemGroup","param":""},{"items":[{"localPosition":"-3.779,2.318,0","localRotation":"0,0,0","localScale":"-0.75,0.75,0.75","material_id":"15020000"},{"localPosition":"-6.426,-1.036,0","localRotation":"0,0,0","localScale":"-0.75,0.75,0.75","material_id":"15020000"},{"localPosition":"-1.154,-1.036,0","localRotation":"0,0,0","localScale":"-0.75,0.75,0.75","material_id":"15020000"},{"localPosition":"-6.27,-0.39,0","localRotation":"0,0,0","localScale":"-0.75,0.75,0.75","material_id":"15020000"},{"localPosition":"-1.3,-0.39,0","localRotation":"0,0,0","localScale":"-0.75,0.75,0.75","material_id":"15020000"},{"localPosition":"-6.01,0.25,0","localRotation":"0,0,0","localScale":"-0.75,0.75,0.75","material_id":"15020000"},{"localPosition":"-1.57,0.25,0","localRotation":"0,0,0","localScale":"-0.75,0.75,0.75","material_id":"15020000"},{"localPosition":"-5.63,0.89,0","localRotation":"0,0,0","localScale":"-0.75,0.75,0.75","material_id":"15020000"},{"localPosition":"-1.93,0.89,0","localRotation":"0,0,0","localScale":"-0.75,0.75,0.75","material_id":"15020000"},{"localPosition":"-5.16,1.54,0","localRotation":"0,0,0","localScale":"-0.75,0.75,0.75","material_id":"15020000"},{"localPosition":"-2.42,1.54,0","localRotation":"0,0,0","localScale":"-0.75,0.75,0.75","material_id":"15020000"},{"localPosition":"-4.5,2.02,0","localRotation":"0,0,0","localScale":"-0.75,0.75,0.75","material_id":"15020000"},{"localPosition":"-3.07,2.02,0","localRotation":"0,0,0","localScale":"-0.75,0.75,0.75","material_id":"15020000"}],"localPosition":"225.38,9.5,0","localRotation":"0,0,0","localScale":"1,1,1","left_x":218,"parentName":"item","luaName":"EliminateItemGroup","param":""},{"localPosition":"221.55,3.65,0","localRotation":"0,0,0","localScale":"1,1,1","left_x":221,"parentName":"bouncing","luaName":"RhubarbDuckPointMark","param":""},{"localPosition":"226,7.5,0","localRotation":"0,0,0","localScale":"4,0.2,7","left_x":224,"parentName":"collider","luaName":"MonoSurface","param":""},{"items":[{"localPosition":"0.44,0.88,0","localRotation":"0,0,0","localScale":"-0.75,0.75,0.75","material_id":"15020000"},{"localPosition":"-0.39,0.88,0","localRotation":"0,0,0","localScale":"-0.75,0.75,0.75","material_id":"15020000"},{"localPosition":"-1.03,0.31,0","localRotation":"0,0,0","localScale":"-0.75,0.75,0.75","material_id":"15020000"},{"localPosition":"-1.03,-0.42,0","localRotation":"0,0,0","localScale":"-0.75,0.75,0.75","material_id":"15020000"},{"localPosition":"0,0.038,0","localRotation":"0,0,0","localScale":"1,1,1","material_id":"15021000"},{"localPosition":"1.04,-0.42,0","localRotation":"0,0,0","localScale":"-0.75,0.75,0.75","material_id":"15020000"},{"localPosition":"1.04,0.31,0","localRotation":"0,0,0","localScale":"-0.75,0.75,0.75","material_id":"15020000"},{"localPosition":"0.44,-0.852,0","localRotation":"0,0,0","localScale":"-0.75,0.75,0.75","material_id":"15020000"},{"localPosition":"-0.39,-0.852,0","localRotation":"0,0,0","localScale":"-0.75,0.75,0.75","material_id":"15020000"}],"localPosition":"226.01,8.85,0","localRotation":"0,0,0","localScale":"1,1,1","left_x":224,"parentName":"item","luaName":"EliminateItemGroup","param":""},{"items":[{"localPosition":"-3.779,2.318,0","localRotation":"0,0,0","localScale":"-0.75,0.75,0.75","material_id":"15020000"},{"localPosition":"-6.426,-1.036,0","localRotation":"0,0,0","localScale":"-0.75,0.75,0.75","material_id":"15020000"},{"localPosition":"-1.154,-1.036,0","localRotation":"0,0,0","localScale":"-0.75,0.75,0.75","material_id":"15020000"},{"localPosition":"-6.27,-0.39,0","localRotation":"0,0,0","localScale":"-0.75,0.75,0.75","material_id":"15020000"},{"localPosition":"-1.3,-0.39,0","localRotation":"0,0,0","localScale":"-0.75,0.75,0.75","material_id":"15020000"},{"localPosition":"-6.01,0.25,0","localRotation":"0,0,0","localScale":"-0.75,0.75,0.75","material_id":"15020000"},{"localPosition":"-1.57,0.25,0","localRotation":"0,0,0","localScale":"-0.75,0.75,0.75","material_id":"15020000"},{"localPosition":"-5.63,0.89,0","localRotation":"0,0,0","localScale":"-0.75,0.75,0.75","material_id":"15020000"},{"localPosition":"-1.93,0.89,0","localRotation":"0,0,0","localScale":"-0.75,0.75,0.75","material_id":"15020000"},{"localPosition":"-5.16,1.54,0","localRotation":"0,0,0","localScale":"-0.75,0.75,0.75","material_id":"15020000"},{"localPosition":"-2.42,1.54,0","localRotation":"0,0,0","localScale":"-0.75,0.75,0.75","material_id":"15020000"},{"localPosition":"-4.5,2.02,0","localRotation":"0,0,0","localScale":"-0.75,0.75,0.75","material_id":"15020000"},{"localPosition":"-3.07,2.02,0","localRotation":"0,0,0","localScale":"-0.75,0.75,0.75","material_id":"15020000"}],"localPosition":"231.31,3.86,0","localRotation":"0,0,0","localScale":"1,1,1","left_x":224,"parentName":"item","luaName":"EliminateItemGroup","param":""},{"items":[{"localPosition":"0.74,0.5,0","localRotation":"0,0,0","localScale":"-0.75,0.75,0.75","material_id":"15020000"},{"localPosition":"0.38,1.1,0","localRotation":"0,0,0","localScale":"-0.75,0.75,0.75","material_id":"15020000"},{"localPosition":"-4.8,2.32,0","localRotation":"0,0,0","localScale":"-0.75,0.75,0.75","material_id":"15020000"},{"localPosition":"-7.44,-1.04,0","localRotation":"0,0,0","localScale":"-0.75,0.75,0.75","material_id":"15020000"},{"localPosition":"1.33,-0.74,0","localRotation":"0,0,0","localScale":"-0.75,0.75,0.75","material_id":"15020000"},{"localPosition":"-7.29,-0.39,0","localRotation":"0,0,0","localScale":"-0.75,0.75,0.75","material_id":"15020000"},{"localPosition":"1.06,-0.12,0","localRotation":"0,0,0","localScale":"-0.75,0.75,0.75","material_id":"15020000"},{"localPosition":"-7.03,0.25,0","localRotation":"0,0,0","localScale":"-0.75,0.75,0.75","material_id":"15020000"},{"localPosition":"-6.65,0.89,0","localRotation":"0,0,0","localScale":"-0.75,0.75,0.75","material_id":"15020000"},{"localPosition":"-6.18,1.54,0","localRotation":"0,0,0","localScale":"-0.75,0.75,0.75","material_id":"15020000"},{"localPosition":"-5.52,2.02,0","localRotation":"0,0,0","localScale":"-0.75,0.75,0.75","material_id":"15020000"},{"localPosition":"-0.01,1.71,0","localRotation":"0,0,0","localScale":"-0.75,0.75,0.75","material_id":"15020000"},{"localPosition":"-0.43,2.28,0","localRotation":"0,0,0","localScale":"-0.75,0.75,0.75","material_id":"15020000"},{"localPosition":"-0.87,2.88,0","localRotation":"0,0,0","localScale":"-0.75,0.75,0.75","material_id":"15020000"},{"localPosition":"-1.31,3.45,0","localRotation":"0,0,0","localScale":"-0.75,0.75,0.75","material_id":"15020000"},{"localPosition":"-1.88,3.96,0","localRotation":"0,0,0","localScale":"-0.75,0.75,0.75","material_id":"15020000"},{"localPosition":"-2.6,4.39,0","localRotation":"0,0,0","localScale":"-0.75,0.75,0.75","material_id":"15020000"},{"localPosition":"-4.13,2.65,0","localRotation":"0,0,0","localScale":"-0.75,0.75,0.75","material_id":"15020000"},{"localPosition":"-3.778,3.304,0","localRotation":"0,0,0","localScale":"-0.75,0.75,0.75","material_id":"15020000"},{"localPosition":"-3.28,3.89,0","localRotation":"0,0,0","localScale":"-0.75,0.75,0.75","material_id":"15020000"}],"localPosition":"235.1916,9.5,0","localRotation":"0,0,0","localScale":"1,1,1","left_x":227,"parentName":"item","luaName":"EliminateItemGroup","param":""},{"collider_center":null,"collider_radius":null,"collider_height":null,"localPosition":"227.61,2.78,0","localRotation":"0,90.00001,0","localScale":"1.199999,1.2,-1.199999","left_x":227,"parentName":"monster","luaName":"KoffingEnemy","param":"15030000"},{"collider_center":null,"collider_radius":null,"collider_height":null,"localPosition":"232.01,6.05,0","localRotation":"0,90.00001,0","localScale":"1.2,1.2,-1.2","left_x":231,"parentName":"monster","luaName":"KoffingEnemy","param":"15030000"},{"collider_center":null,"collider_radius":null,"collider_height":null,"localPosition":"232.01,8.02,0","localRotation":"0,90.00001,0","localScale":"1.2,1.2,-1.2","left_x":231,"parentName":"monster","luaName":"KoffingEnemy","param":"15030000"},{"collider_center":null,"collider_radius":null,"collider_height":null,"localPosition":"232.01,10.04,0","localRotation":"0,90.00001,0","localScale":"1.199999,1.2,-1.199999","left_x":231,"parentName":"monster","luaName":"KoffingEnemy","param":"15030000"},{"step_localPosition":"0,0.75,0","step_localScale":"2.5,1,6","bouncing_model_name":"jelly_yellow","bouncing_model_localPosition":"0,0,0","bouncing_model_localRotation":"2.504478E-06,0,0","bouncing_model_localScale":"1,1,1","target_localPosition":"","bouncing_path":[{"speed":15.0,"delay":0.0,"loopType":"none","easeType":"easeOutExpo","rotateAngle":"0,0,0","nodes":["0.6126862,0.934468,0","4.429321,1.691375,0"]}],"localPosition":"238.49,1.5,0","localRotation":"0,0,0","localScale":"1,1,1","left_x":236,"parentName":"bouncing","luaName":"BouncingSurface","param":"60;3;0;0;1","m_TargetZ":0.0,"m_isReplaceAction":1.0,"m_Direction":1.0,"m_ActionSpeed":1.0,"m_ActionDelayTime":0.0},{"step_localPosition":"0,0.79,0","step_localScale":"2.5,1,6","bouncing_model_name":"jelly_yellow","bouncing_model_localPosition":"0,0,0","bouncing_model_localRotation":"2.504478E-06,0,0","bouncing_model_localScale":"1,1,1","target_localPosition":"","bouncing_path":[{"speed":15.0,"delay":0.0,"loopType":"none","easeType":"easeOutExpo","rotateAngle":"0,0,0","nodes":["0.6791382,0.9351561,0","4.370621,1.816418,0"]}],"localPosition":"241.06,2,0","localRotation":"0,0,0","localScale":"1,1,1","left_x":239,"parentName":"bouncing","luaName":"BouncingSurface","param":"60;3;0;0;1","m_TargetZ":0.0,"m_isReplaceAction":1.0,"m_Direction":1.0,"m_ActionSpeed":1.0,"m_ActionDelayTime":0.0},{"step_localPosition":"0.07,0.75,0","step_localScale":"3,1,6","bouncing_model_name":"jelly_yellow","bouncing_model_localPosition":"0,0,0","bouncing_model_localRotation":"2.504478E-06,0,0","bouncing_model_localScale":"1,1,1","target_localPosition":"","bouncing_path":[{"speed":25.0,"delay":0.0,"loopType":"none","easeType":"easeOutExpo","rotateAngle":"0,0,0","nodes":["0,0.8706377,0","16.07115,17.66214,0"]}],"localPosition":"243.77,2.5,0","localRotation":"0,0,0","localScale":"1,1,1","left_x":242,"parentName":"bouncing","luaName":"BouncingSurface","param":"60;3;0","m_TargetZ":0.0,"m_isReplaceAction":1.0,"m_Direction":1.0,"m_ActionSpeed":1.0,"m_ActionDelayTime":0.0},{"step_localPosition":"0,0.4,0","step_localScale":"3,0.4,6","bouncing_model_name":"jelly_yellow","bouncing_model_localPosition":"0,0,0","bouncing_model_localRotation":"330,180,180","bouncing_model_localScale":"1,1,1","target_localPosition":"","bouncing_path":[{"speed":20.0,"delay":0.0,"loopType":"none","easeType":"easeOutExpo","rotateAngle":"0,0,0","nodes":["0,0,0","10.91423,-18.28548,0"]}],"localPosition":"250.95,10.54,0","localRotation":"0,0,0","localScale":"1,1,1","left_x":249,"parentName":"bouncing","luaName":"BouncingSurface","param":"60;3;0","m_TargetZ":0.0,"m_isReplaceAction":1.0,"m_Direction":1.0,"m_ActionSpeed":1.0,"m_ActionDelayTime":0.0},{"step_localPosition":"0,0.4,0","step_localScale":"3,0.4,6","bouncing_model_name":"jelly_yellow","bouncing_model_localPosition":"0,0,0","bouncing_model_localRotation":"0,0,340","bouncing_model_localScale":"1,1,1","target_localPosition":"","bouncing_path":[{"speed":20.0,"delay":0.0,"loopType":"none","easeType":"easeOutQuint","rotateAngle":"0,0,0","nodes":["0.6719971,1.532387,0","8.79129,11.38162,0","15.20505,9.769027,0","21.4631,-2.117588,0"]}],"localPosition":"256.11,1.29,0","localRotation":"0,0,0","localScale":"1.3,1.3,1.3","left_x":254,"parentName":"bouncing","luaName":"BouncingSurface","param":"60;3;0","m_TargetZ":0.0,"m_isReplaceAction":1.0,"m_Direction":1.0,"m_ActionSpeed":1.0,"m_ActionDelayTime":0.0},{"localPosition":"255.14,2.68,0","localRotation":"0,0,0","localScale":"1,1,1","left_x":254,"parentName":"bouncing","luaName":"RevivePointMark","param":""},{"playerWallData_Right":null,"playerWallData_Left":null,"localPosition":"279,-3,0","localRotation":"0,0,0","localScale":"8,6,7","left_x":275,"parentName":"collider","luaName":"FlatSurface","param":""},{"localPosition":"275.68,0.51,0","localRotation":"0,0,0","localScale":"1,1,1","left_x":275,"parentName":"bouncing","luaName":"RevivePointMark","param":""},{"localPosition":"277.39,1.73,0","localRotation":"0,0,0","localScale":"1,1,1","left_x":276,"parentName":"bouncing","luaName":"RhubarbDuckPointMark","param":""},{"localPosition":"276.53,1.37,0","localRotation":"0,0,0","localScale":"1,1,1","left_x":276,"parentName":"bouncing","luaName":"BouncingBlockItem","param":""},{"localPosition":"276.91,0.61,0","localRotation":"0,0,0","localScale":"1,1,1","left_x":276,"parentName":"bouncing","luaName":"HolyLandingPointMark","param":""}]